{
  "adsType": 1,
  "displayInfo": "",
  "channelName": "要闻",
  "loadtime": 1551342455279,
  "articles": [
    {
      "template": 1,
      "mediaId": "6183527926412083215",
      "recreason": 1,
      "createTime": 1551327660,
      "recommendEvent": 0,
      "virtualTime": 1551342455266,
      "keyword": "经济 外交",
      "score": 0.3631509913380488,
      "mediaName": "环球网",
      "state": 0,
      "isRec": 0,
      "contentType": 1,
      "picNum": 1,
      "articleUrl": "http://c.cdn.sohu.com/article/6506743439009253377",
      "commentNum": 2,
      "filterWords": [
        {
          "name": "屏蔽来源:环球网",
          "type": "media"
        },
        {
          "name": "不想看:经济",
          "type": "keyword"
        },
        {
          "name": "不想看:外交",
          "type": "keyword"
        },
        {
          "name": "不感兴趣",
          "type": "unlike"
        }
      ],
      "pics": [
        {
          "height": 640,
          "width": 960,
          "url": "http://p.cdn.sohu.com/18fd4bda/057781582388892ebcc0d51936ecc896.jpeg"
        }
      ],
      "title": "金正恩：美在平壤设联络处皆大欢喜",
      "category": {
        "id": 100,
        "name": "其他"
      },
      "newsId": "6506743439009253377",
      "playCount": 0,
      "recpool": 0,
      "isTop": 0
    },
    {
      "template": 3,
      "mediaId": "6183527926412083214",
      "recreason": 1,
      "createTime": 1551320120,
      "recommendEvent": 0,
      "virtualTime": 1551342388600,
      "keyword": "脱欧 外交",
      "score": 0.2812411786972869,
      "mediaName": "中国新闻网",
      "state": 0,
      "isRec": 0,
      "contentType": 1,
      "picNum": 4,
      "articleUrl": "http://c.cdn.sohu.com/article/6506708201201731584",
      "commentNum": 4,
      "filterWords": [
        {
          "name": "屏蔽来源:中国新闻网",
          "type": "media"
        },
        {
          "name": "不想看:脱欧",
          "type": "keyword"
        },
        {
          "name": "不想看:外交",
          "type": "keyword"
        },
        {
          "name": "不感兴趣",
          "type": "unlike"
        }
      ],
      "pics": [
        {
          "height": 437,
          "width": 617,
          "url": "http://p.cdn.sohu.com/covers/18fd4bda/af35bf926acd0ae6b765488037329de5.jpeg"
        },
        {
          "height": 402,
          "width": 567,
          "url": "http://p.cdn.sohu.com/covers/18fd4bda/a38ceb334f8bf11e57a219f7c41b2551.jpeg"
        },
        {
          "height": 353,
          "width": 499,
          "url": "http://p.cdn.sohu.com/covers/18fd4bda/11973e4109ba2c3f82eddd0dd6257e59.jpeg"
        }
      ],
      "title": "“脱欧”紧要关头 伦敦和平上演“街头战”",
      "category": {
        "id": 100,
        "name": "其他"
      },
      "newsId": "6506708201201731584",
      "playCount": 0,
      "recpool": 0,
      "isTop": 0
    },
    {
      "template": 3,
      "mediaId": "6488757160128806913",
      "recreason": 1,
      "createTime": 1551317408,
      "recommendEvent": 0,
      "virtualTime": 1551342321934,
      "keyword": "刁磊 何洁 音乐",
      "score": 0.21655130967494657,
      "mediaName": "长春国贸娱乐",
      "state": 0,
      "isRec": 0,
      "contentType": 1,
      "picNum": 7,
      "articleUrl": "http://c.cdn.sohu.com/article/6506696850987288577",
      "commentNum": 2,
      "filterWords": [
        {
          "name": "屏蔽来源:长春国贸娱乐",
          "type": "media"
        },
        {
          "name": "不想看:刁磊",
          "type": "keyword"
        },
        {
          "name": "不想看:何洁",
          "type": "keyword"
        },
        {
          "name": "不想看:音乐",
          "type": "keyword"
        },
        {
          "name": "不感兴趣",
          "type": "unlike"
        }
      ],
      "pics": [
        {
          "height": 444,
          "width": 578,
          "url": "http://p.cdn.sohu.com/18fd4bda/77952c58f9caf6c1c8cc300fbcad4205.jpeg"
        },
        {
          "height": 408,
          "width": 576,
          "url": "http://p.cdn.sohu.com/covers/18fd4bda/17c0fb7d99c5cc0b7144e0710f17c764.jpeg"
        },
        {
          "height": 400,
          "width": 581,
          "url": "http://p.cdn.sohu.com/18fd4bda/9bbba6b763916e5073c0c5435b4d90cf.jpeg"
        }
      ],
      "title": "何洁老公刁磊20年前旧照曝光，那时候的他长这样！",
      "category": {
        "id": 100,
        "name": "其他"
      },
      "newsId": "6506696850987288577",
      "playCount": 0,
      "recpool": 0,
      "isTop": 0
    },
    {
      "template": 1,
      "mediaId": "6383531400028487681",
      "recreason": 1,
      "createTime": 1551328822,
      "recommendEvent": 0,
      "virtualTime": 1551342255268,
      "keyword": "布托 战斗机 国际",
      "score": 0.21099409540224107,
      "mediaName": "环球时报国际",
      "state": 0,
      "isRec": 0,
      "contentType": 1,
      "picNum": 3,
      "articleUrl": "http://c.cdn.sohu.com/article/6506744704296552448",
      "commentNum": 504,
      "filterWords": [
        {
          "name": "屏蔽来源:环球时报国际",
          "type": "media"
        },
        {
          "name": "不想看:布托",
          "type": "keyword"
        },
        {
          "name": "不想看:战斗机",
          "type": "keyword"
        },
        {
          "name": "不想看:国际",
          "type": "keyword"
        },
        {
          "name": "不感兴趣",
          "type": "unlike"
        }
      ],
      "pics": [
        {
          "height": 361,
          "width": 510,
          "url": "http://p.cdn.sohu.com/covers/18fd4bda/0a3b579251543cd6b15e07266978100e.jpeg"
        }
      ],
      "title": "巴基斯坦布托家族成员撰文呼吁释放被俘印度飞行员",
      "category": {
        "id": 100,
        "name": "其他"
      },
      "newsId": "6506744704296552448",
      "playCount": 0,
      "recpool": 0,
      "isTop": 0
    },
    {
      "template": 1,
      "mediaId": "6204971772371009537",
      "recreason": 1,
      "createTime": 1551323773,
      "recommendEvent": 0,
      "virtualTime": 1551342188602,
      "keyword": "佩工 英超 足球",
      "score": 0.20441871032941683,
      "mediaName": "虎扑",
      "state": 0,
      "isRec": 0,
      "contentType": 1,
      "picNum": 1,
      "articleUrl": "http://c.cdn.sohu.com/article/6506723598571407361",
      "commentNum": 0,
      "filterWords": [
        {
          "name": "屏蔽来源:虎扑",
          "type": "media"
        },
        {
          "name": "不想看:佩工",
          "type": "keyword"
        },
        {
          "name": "不想看:英超",
          "type": "keyword"
        },
        {
          "name": "不想看:足球",
          "type": "keyword"
        },
        {
          "name": "不感兴趣",
          "type": "unlike"
        }
      ],
      "pics": [
        {
          "height": 639,
          "width": 960,
          "url": "http://p.cdn.sohu.com/18fd4bda/6b1f7728019924e9df90062735a40e1c.jpeg"
        }
      ],
      "title": "佩工：曼城的点球并非点球，看到他们拖时间不多见",
      "category": {
        "id": 100,
        "name": "其他"
      },
      "newsId": "6506723598571407361",
      "playCount": 0,
      "recpool": 0,
      "isTop": 0
    },
    {
      "template": 1,
      "mediaId": "6183527926412083214",
      "recreason": 1,
      "createTime": 1551332657,
      "recommendEvent": 0,
      "virtualTime": 1551342121936,
      "keyword": "人人车 裁员 互联网",
      "score": 0.20365456998169382,
      "mediaName": "中国新闻网",
      "state": 0,
      "isRec": 0,
      "contentType": 1,
      "picNum": 1,
      "articleUrl": "http://c.cdn.sohu.com/article/6506763200862619648",
      "commentNum": 0,
      "filterWords": [
        {
          "name": "屏蔽来源:中国新闻网",
          "type": "media"
        },
        {
          "name": "不想看:人人车",
          "type": "keyword"
        },
        {
          "name": "不想看:裁员",
          "type": "keyword"
        },
        {
          "name": "不想看:互联网",
          "type": "keyword"
        },
        {
          "name": "不感兴趣",
          "type": "unlike"
        }
      ],
      "pics": [
        {
          "height": 367,
          "width": 550,
          "url": "http://p.cdn.sohu.com/10660c57/c148543a91c5da11652e06d9b4ff3d0f.jpeg"
        }
      ],
      "title": "变相裁员?人人车被曝未离职员工每天打卡三次 官方回应",
      "category": {
        "id": 100,
        "name": "其他"
      },
      "newsId": "6506763200862619648",
      "playCount": 0,
      "recpool": 0,
      "isTop": 0
    },
    {
      "template": 3,
      "mediaId": "6488757160128806913",
      "recreason": 1,
      "createTime": 1551258546,
      "recommendEvent": 0,
      "virtualTime": 1551342055270,
      "keyword": "许晴 老炮儿 八卦",
      "score": 0.18900453362861194,
      "mediaName": "长春国贸娱乐",
      "state": 0,
      "isRec": 0,
      "contentType": 1,
      "picNum": 6,
      "articleUrl": "http://c.cdn.sohu.com/article/6506449991765067776",
      "commentNum": 115,
      "filterWords": [
        {
          "name": "屏蔽来源:长春国贸娱乐",
          "type": "media"
        },
        {
          "name": "不想看:许晴",
          "type": "keyword"
        },
        {
          "name": "不想看:老炮儿",
          "type": "keyword"
        },
        {
          "name": "不想看:八卦",
          "type": "keyword"
        },
        {
          "name": "不感兴趣",
          "type": "unlike"
        }
      ],
      "pics": [
        {
          "height": 363,
          "width": 513,
          "url": "http://p.cdn.sohu.com/covers/18fd4bda/0091f5e38489421dd96ded76dd809958.jpeg"
        },
        {
          "height": 440,
          "width": 511,
          "url": "http://p.cdn.sohu.com/18fd4bda/240a05f86fe4b8e2484fa0ba7d64d588.jpeg"
        },
        {
          "height": 365,
          "width": 515,
          "url": "http://p.cdn.sohu.com/covers/18fd4bda/b8671a170b3ebe4f9dcbaac0a9b74097.jpeg"
        }
      ],
      "title": "50岁许晴近照曝光，路人镜头下的她是这样的！",
      "category": {
        "id": 100,
        "name": "其他"
      },
      "newsId": "6506449991765067776",
      "playCount": 0,
      "recpool": 0,
      "isTop": 0
    },
    {
      "template": 1,
      "mediaId": "6204971772371009537",
      "recreason": 1,
      "createTime": 1551324609,
      "recommendEvent": 0,
      "virtualTime": 1551341988604,
      "keyword": "沙拉木 银魂 动漫",
      "score": 0.22885139502105956,
      "mediaName": "虎扑",
      "state": 0,
      "isRec": 0,
      "contentType": 1,
      "picNum": 2,
      "articleUrl": "http://c.cdn.sohu.com/article/6506727058981259265",
      "commentNum": 1,
      "filterWords": [
        {
          "name": "屏蔽来源:虎扑",
          "type": "media"
        },
        {
          "name": "不想看:沙拉木",
          "type": "keyword"
        },
        {
          "name": "不想看:银魂",
          "type": "keyword"
        },
        {
          "name": "不想看:动漫",
          "type": "keyword"
        },
        {
          "name": "不感兴趣",
          "type": "unlike"
        }
      ],
      "pics": [
        {
          "height": 300,
          "width": 660,
          "url": "http://p.cdn.sohu.com/18fd4bda/ef448d6014fb19bbb69ccd2dd0094fec.jpeg"
        }
      ],
      "title": "名字太长也烦恼！阿不都沙拉木转发恶搞动漫自嘲",
      "category": {
        "id": 100,
        "name": "其他"
      },
      "newsId": "6506727058981259265",
      "playCount": 0,
      "recpool": 0,
      "isTop": 0
    },
    {
      "template": 3,
      "mediaId": "6488288686440972289",
      "recreason": 1,
      "createTime": 1551311405,
      "recommendEvent": 0,
      "virtualTime": 1551341921938,
      "keyword": "黄晓明 baby 八卦",
      "score": 0.15605219175562599,
      "mediaName": "猫眼娱乐",
      "state": 0,
      "isRec": 0,
      "contentType": 1,
      "picNum": 4,
      "articleUrl": "http://c.cdn.sohu.com/article/6506671668037945344",
      "commentNum": 2,
      "filterWords": [
        {
          "name": "屏蔽来源:猫眼娱乐",
          "type": "media"
        },
        {
          "name": "不想看:黄晓明",
          "type": "keyword"
        },
        {
          "name": "不想看:baby",
          "type": "keyword"
        },
        {
          "name": "不想看:八卦",
          "type": "keyword"
        },
        {
          "name": "不感兴趣",
          "type": "unlike"
        }
      ],
      "pics": [
        {
          "height": 332,
          "width": 469,
          "url": "http://p.cdn.sohu.com/covers/18fd4bda/bd0d443420799d9ba179c034e02e2f53.jpeg"
        },
        {
          "height": 243,
          "width": 440,
          "url": "http://p.cdn.sohu.com/18fd4bda/a3eb975eb402148a95acb78ad47a3dd9.jpeg"
        },
        {
          "height": 246,
          "width": 440,
          "url": "http://p.cdn.sohu.com/18fd4bda/5879d04c9d3b0d3b67088ada93a33557.jpeg"
        }
      ],
      "title": "黄晓明零点发博为baby庆生，小海绵出镜发量瞩目",
      "category": {
        "id": 100,
        "name": "其他"
      },
      "newsId": "6506671668037945344",
      "playCount": 0,
      "recpool": 0,
      "isTop": 0
    },
    {
      "template": 4,
      "mediaId": "6183529071108948012",
      "recreason": 1,
      "createTime": 1551323122,
      "recommendEvent": 0,
      "virtualTime": 1551341855272,
      "keyword": "普京 数字货币 国际",
      "score": 0.22076088809909294,
      "mediaName": "财经网",
      "state": 0,
      "isRec": 0,
      "contentType": 1,
      "picNum": 0,
      "articleUrl": "http://c.cdn.sohu.com/article/6506720787494340608",
      "commentNum": 0,
      "filterWords": [
        {
          "name": "屏蔽来源:财经网",
          "type": "media"
        },
        {
          "name": "不想看:普京",
          "type": "keyword"
        },
        {
          "name": "不想看:数字货币",
          "type": "keyword"
        },
        {
          "name": "不想看:国际",
          "type": "keyword"
        },
        {
          "name": "不感兴趣",
          "type": "unlike"
        }
      ],
      "pics": [],
      "title": "俄罗斯总统普京下令在7月前执行加密货币法规",
      "category": {
        "id": 100,
        "name": "其他"
      },
      "newsId": "6506720787494340608",
      "playCount": 0,
      "recpool": 0,
      "isTop": 0
    },
    {
      "template": 3,
      "mediaId": "6183527926412083215",
      "recreason": 1,
      "createTime": 1551330659,
      "recommendEvent": 0,
      "virtualTime": 1551342527439,
      "keyword": "特朗普 外交",
      "score": 0.2316870619270244,
      "mediaName": "环球网",
      "state": 0,
      "isRec": 0,
      "contentType": 1,
      "picNum": 3,
      "articleUrl": "http://c.cdn.sohu.com/article/6506752553445754880",
      "commentNum": 0,
      "filterWords": [
        {
          "name": "屏蔽来源:环球网",
          "type": "media"
        },
        {
          "name": "不想看:特朗普",
          "type": "keyword"
        },
        {
          "name": "不想看:外交",
          "type": "keyword"
        },
        {
          "name": "不感兴趣",
          "type": "unlike"
        }
      ],
      "pics": [
        {
          "height": 640,
          "width": 960,
          "url": "http://p.cdn.sohu.com/18fd4bda/d5b53019694a5d7a465c132780276fbb.jpeg"
        },
        {
          "height": 639,
          "width": 960,
          "url": "http://p.cdn.sohu.com/18fd4bda/8912374f3bd50640c38aaa9461673eb7.jpeg"
        },
        {
          "height": 639,
          "width": 960,
          "url": "http://p.cdn.sohu.com/18fd4bda/86bb15d9b52a5caf995bc124e6b44810.jpeg"
        }
      ],
      "title": "金正恩称如不愿无核化不会来越南 特朗普这么评论",
      "category": {
        "id": 100,
        "name": "其他"
      },
      "newsId": "6506752553445754880",
      "playCount": 0,
      "recpool": 0,
      "isTop": 0
    },
    {
      "template": 3,
      "mediaId": "6183527926412083215",
      "recreason": 1,
      "createTime": 1551261422,
      "recommendEvent": 0,
      "virtualTime": 1551342524767,
      "keyword": "空军 战斗机 要闻",
      "score": 0.1498475935141695,
      "mediaName": "环球网",
      "state": 0,
      "isRec": 0,
      "contentType": 1,
      "picNum": 9,
      "articleUrl": "http://c.cdn.sohu.com/article/6506470280905361408",
      "commentNum": 86,
      "filterWords": [
        {
          "name": "屏蔽来源:环球网",
          "type": "media"
        },
        {
          "name": "不想看:空军",
          "type": "keyword"
        },
        {
          "name": "不想看:战斗机",
          "type": "keyword"
        },
        {
          "name": "不想看:要闻",
          "type": "keyword"
        },
        {
          "name": "不感兴趣",
          "type": "unlike"
        }
      ],
      "pics": [
        {
          "height": 414,
          "width": 584,
          "url": "http://p.cdn.sohu.com/covers/10660c57/547cc26d0efd31c7e513c83f2727fed1.jpeg"
        },
        {
          "height": 374,
          "width": 528,
          "url": "http://p.cdn.sohu.com/covers/10660c57/bf7895db7205866d1f9409993ee6c365.jpeg"
        },
        {
          "height": 717,
          "width": 957,
          "url": "http://p.cdn.sohu.com/10660c57/70cb2e863e76c1331c4d9ebbf8627f35.jpeg"
        }
      ],
      "title": "印度被俘飞行员身份确认 系一名战斗机中队指挥官",
      "category": {
        "id": 100,
        "name": "其他"
      },
      "newsId": "6506470280905361408",
      "playCount": 0,
      "recpool": 0,
      "isTop": 0
    },
    {
      "template": 1,
      "mediaId": "6183527933882138630",
      "recreason": 1,
      "createTime": 1551324694,
      "recommendEvent": 0,
      "virtualTime": 1551342522095,
      "keyword": "伍正禧 南京大屠杀 军事史",
      "score": 0.14864412842557817,
      "mediaName": "澎湃新闻",
      "state": 0,
      "isRec": 0,
      "contentType": 1,
      "picNum": 2,
      "articleUrl": "http://c.cdn.sohu.com/article/6506732117030864897",
      "commentNum": 0,
      "filterWords": [
        {
          "name": "屏蔽来源:澎湃新闻",
          "type": "media"
        },
        {
          "name": "不想看:伍正禧",
          "type": "keyword"
        },
        {
          "name": "不想看:南京大屠杀",
          "type": "keyword"
        },
        {
          "name": "不想看:军事史",
          "type": "keyword"
        },
        {
          "name": "不感兴趣",
          "type": "unlike"
        }
      ],
      "pics": [
        {
          "height": 236,
          "width": 333,
          "url": "http://p.cdn.sohu.com/covers/273f1e40/f76df3dc6ba20c740999d6882f8f0739.jpeg"
        }
      ],
      "title": "南京大屠杀幸存者伍正禧去世 2天内2名幸存者离世",
      "category": {
        "id": 100,
        "name": "其他"
      },
      "newsId": "6506732117030864897",
      "playCount": 0,
      "recpool": 0,
      "isTop": 0
    },
    {
      "template": 1,
      "mediaId": "6183527926412083214",
      "recreason": 1,
      "createTime": 1551330615,
      "recommendEvent": 0,
      "virtualTime": 1551342519423,
      "keyword": "徐灿成 拳击 格斗",
      "score": 0.14418621477296142,
      "mediaName": "中国新闻网",
      "state": 0,
      "isRec": 0,
      "contentType": 1,
      "picNum": 2,
      "articleUrl": "http://c.cdn.sohu.com/article/6506753801356052480",
      "commentNum": 0,
      "filterWords": [
        {
          "name": "屏蔽来源:中国新闻网",
          "type": "media"
        },
        {
          "name": "不想看:徐灿成",
          "type": "keyword"
        },
        {
          "name": "不想看:拳击",
          "type": "keyword"
        },
        {
          "name": "不想看:格斗",
          "type": "keyword"
        },
        {
          "name": "不感兴趣",
          "type": "unlike"
        }
      ],
      "pics": [
        {
          "height": 550,
          "width": 550,
          "url": "http://p.cdn.sohu.com/27ded251/04a0d9777320a02f37b407474013a74a.jpeg"
        }
      ],
      "title": "历史性突破 徐灿成中国首位五星级拳王(图)",
      "category": {
        "id": 100,
        "name": "其他"
      },
      "newsId": "6506753801356052480",
      "playCount": 0,
      "recpool": 0,
      "isTop": 0
    },
    {
      "template": 4,
      "mediaId": "6183527952077029418",
      "recreason": 1,
      "createTime": 1551320112,
      "recommendEvent": 0,
      "virtualTime": 1551342516751,
      "keyword": "网络安全 信息安全 外交",
      "score": 0.1712325422501932,
      "mediaName": "参考消息",
      "state": 0,
      "isRec": 0,
      "contentType": 1,
      "picNum": 0,
      "articleUrl": "http://c.cdn.sohu.com/article/6506708159648761857",
      "commentNum": 0,
      "filterWords": [
        {
          "name": "屏蔽来源:参考消息",
          "type": "media"
        },
        {
          "name": "不想看:网络安全",
          "type": "keyword"
        },
        {
          "name": "不想看:信息安全",
          "type": "keyword"
        },
        {
          "name": "不想看:外交",
          "type": "keyword"
        },
        {
          "name": "不感兴趣",
          "type": "unlike"
        }
      ],
      "pics": [],
      "title": "美高官妄称中国网络安全法是“装满弹药的武器” 俄媒：贼喊捉贼",
      "category": {
        "id": 100,
        "name": "其他"
      },
      "newsId": "6506708159648761857",
      "playCount": 0,
      "recpool": 0,
      "isTop": 0
    },
    {
      "template": 3,
      "mediaId": "6204971772371009537",
      "recreason": 1,
      "createTime": 1551304807,
      "recommendEvent": 0,
      "virtualTime": 1551342514079,
      "keyword": "范戴克 阿诺 足球",
      "score": 0.20154112694195853,
      "mediaName": "虎扑",
      "state": 0,
      "isRec": 0,
      "contentType": 1,
      "picNum": 23,
      "articleUrl": "http://c.cdn.sohu.com/article/6506644063100340225",
      "commentNum": 0,
      "filterWords": [
        {
          "name": "屏蔽来源:虎扑",
          "type": "media"
        },
        {
          "name": "不想看:范戴克",
          "type": "keyword"
        },
        {
          "name": "不想看:阿诺",
          "type": "keyword"
        },
        {
          "name": "不想看:足球",
          "type": "keyword"
        },
        {
          "name": "不感兴趣",
          "type": "unlike"
        }
      ],
      "pics": [
        {
          "height": 385,
          "width": 654,
          "url": "http://p.cdn.sohu.com/18fd4bda/85f9c2560c92352e2acf1b2f88db8c1e.jpeg"
        },
        {
          "height": 201,
          "width": 396,
          "url": "http://p.cdn.sohu.com/covers/18fd4bda/8722b3b92681de852cc3b13ce0ab0ce3.jpeg"
        },
        {
          "height": 201,
          "width": 396,
          "url": "http://p.cdn.sohu.com/covers/18fd4bda/10e3c954c1fdd2d9cf5183e20ca07bcc.jpeg"
        }
      ],
      "title": "马内范戴克各两球阿诺大助攻戴帽，利物浦5-0沃特福德",
      "category": {
        "id": 100,
        "name": "其他"
      },
      "newsId": "6506644063100340225",
      "playCount": 0,
      "recpool": 0,
      "isTop": 0
    },
    {
      "template": 3,
      "mediaId": "6204971772371009537",
      "recreason": 1,
      "createTime": 1551308403,
      "recommendEvent": 0,
      "virtualTime": 1551342511407,
      "keyword": "NBA 篮球 要闻",
      "score": 0.19899907254973034,
      "mediaName": "虎扑",
      "state": 0,
      "isRec": 0,
      "contentType": 1,
      "picNum": 5,
      "articleUrl": "http://c.cdn.sohu.com/article/6506659068671690753",
      "commentNum": 8,
      "filterWords": [
        {
          "name": "屏蔽来源:虎扑",
          "type": "media"
        },
        {
          "name": "不想看:NBA",
          "type": "keyword"
        },
        {
          "name": "不想看:篮球",
          "type": "keyword"
        },
        {
          "name": "不想看:要闻",
          "type": "keyword"
        },
        {
          "name": "不感兴趣",
          "type": "unlike"
        }
      ],
      "pics": [
        {
          "height": 680,
          "width": 960,
          "url": "http://p.cdn.sohu.com/covers/18fd4bda/d9d8b30d2a2efbb57b30ea30c22336a4.jpeg"
        },
        {
          "height": 771,
          "width": 960,
          "url": "http://p.cdn.sohu.com/18fd4bda/40ec09d10db927f4ef5414798e593f9d.jpeg"
        },
        {
          "height": 680,
          "width": 960,
          "url": "http://p.cdn.sohu.com/covers/18fd4bda/1744ef8d0b1e7f1801853da52ab96598.jpeg"
        }
      ],
      "title": "火箭众将抵达比赛场馆：塔克手提球鞋出镜",
      "category": {
        "id": 100,
        "name": "其他"
      },
      "newsId": "6506659068671690753",
      "playCount": 0,
      "recpool": 0,
      "isTop": 0
    },
    {
      "template": 3,
      "mediaId": "6204972461977501697",
      "recreason": 1,
      "createTime": 1551324252,
      "recommendEvent": 0,
      "virtualTime": 1551342508735,
      "keyword": "交通 建筑 法律",
      "score": 0.18247259761036977,
      "mediaName": "看看新闻Knews",
      "state": 0,
      "isRec": 0,
      "contentType": 1,
      "picNum": 3,
      "articleUrl": "http://c.cdn.sohu.com/article/6506725553813325825",
      "commentNum": 1,
      "filterWords": [
        {
          "name": "屏蔽来源:看看新闻Knews",
          "type": "media"
        },
        {
          "name": "不想看:交通",
          "type": "keyword"
        },
        {
          "name": "不想看:建筑",
          "type": "keyword"
        },
        {
          "name": "不想看:法律",
          "type": "keyword"
        },
        {
          "name": "不感兴趣",
          "type": "unlike"
        }
      ],
      "pics": [
        {
          "height": 424,
          "width": 640,
          "url": "http://p.cdn.sohu.com/18fd4bda/eaf732e6af99bd30beaf2ae7992b6397.jpeg"
        },
        {
          "height": 360,
          "width": 640,
          "url": "http://p.cdn.sohu.com/18fd4bda/5180809a4529b50bb2a3107b8f760b96.jpeg"
        },
        {
          "height": 426,
          "width": 640,
          "url": "http://p.cdn.sohu.com/18fd4bda/f28a72c8190310bed2ca6cbd07d50af1.jpeg"
        }
      ],
      "title": "埃及火车爆炸起火监控曝光 未减速撞上水泥护栏",
      "category": {
        "id": 100,
        "name": "其他"
      },
      "newsId": "6506725553813325825",
      "playCount": 0,
      "recpool": 0,
      "isTop": 0
    },
    {
      "template": 3,
      "mediaId": "6183527926412083214",
      "recreason": 1,
      "createTime": 1551320459,
      "recommendEvent": 0,
      "virtualTime": 1551342506063,
      "keyword": "特朗普 外交",
      "score": 0.17405564707626056,
      "mediaName": "中国新闻网",
      "state": 0,
      "isRec": 0,
      "contentType": 1,
      "picNum": 3,
      "articleUrl": "http://c.cdn.sohu.com/article/6506711625653815297",
      "commentNum": 0,
      "filterWords": [
        {
          "name": "屏蔽来源:中国新闻网",
          "type": "media"
        },
        {
          "name": "不想看:特朗普",
          "type": "keyword"
        },
        {
          "name": "不想看:外交",
          "type": "keyword"
        },
        {
          "name": "不感兴趣",
          "type": "unlike"
        }
      ],
      "pics": [
        {
          "height": 366,
          "width": 550,
          "url": "http://p.cdn.sohu.com/273f1e40/d1245e18e9616c206f2f7ed7056903aa.jpeg"
        },
        {
          "height": 366,
          "width": 550,
          "url": "http://p.cdn.sohu.com/273f1e40/89509f78312a0ea59aed90ba201de7f1.jpeg"
        },
        {
          "height": 366,
          "width": 550,
          "url": "http://p.cdn.sohu.com/273f1e40/167ae93b6d30918dd5fb159cd8f500c1.jpeg"
        }
      ],
      "title": "特朗普与金正恩27日会晤都说了啥 对话全文公布",
      "category": {
        "id": 100,
        "name": "其他"
      },
      "newsId": "6506711625653815297",
      "playCount": 0,
      "recpool": 0,
      "isTop": 0
    },
    {
      "template": 1,
      "mediaId": "6183527945185787977",
      "recreason": 1,
      "createTime": 1551288567,
      "recommendEvent": 0,
      "virtualTime": 1551342503391,
      "keyword": "外交",
      "score": 0.15590629860566116,
      "mediaName": "外交部网站",
      "state": 0,
      "isRec": 0,
      "contentType": 1,
      "picNum": 0,
      "articleUrl": "http://c.cdn.sohu.com/article/6506615384349607936",
      "commentNum": 37,
      "filterWords": [
        {
          "name": "屏蔽来源:外交部网站",
          "type": "media"
        },
        {
          "name": "不想看:外交",
          "type": "keyword"
        },
        {
          "name": "不感兴趣",
          "type": "unlike"
        }
      ],
      "pics": [
        {
          "height": 426,
          "width": 640,
          "url": "http://p.cdn.sohu.com/f5300f8a/thumb/413f49dea4f3926597c9ba2fbb4ffa69.webp"
        }
      ],
      "title": "巴基斯坦外长深夜紧急给王毅打电话 通报巴印局势",
      "category": {
        "id": 100,
        "name": "其他"
      },
      "newsId": "6506615384349607936",
      "playCount": 0,
      "recpool": 0,
      "isTop": 0
    }
  ],
  "channelId": 148,
  "ip": "180.111.35.250",
  "city": "栖霞区",
  "message": "success",
  "totalNum": 10,
  "exts": "chan:o,home:N_T,rank:o,NH:o2,UCF:o,loadId:885e943802b40,ins_Tag:T_D,homeRecall:model,EE:o,INeg:n,video:O_O,ICF:o2",
  "reqtype": 0,
  "supplement": 1,
  "errorCode": 0,
  "adcode": "320113",
  "ads": "",
  "loadid": "885e943802b40"
}