{
  "adsType": 0,
  "displayInfo": "",
  "channelName": "育儿",
  "loadtime": 1550824245434,
  "articles": [
    {
      "abs": "",
      "articleUrl": "http://c.cdn.sohu.com/article/6504293370507036672",
      "category": {
        "id": 100,
        "name": "其他"
      },
      "commentNum": 0,
      "contentType": 3,
      "createTime": 1550740567,
      "filterWords": [
        {
          "name": "屏蔽来源:这里说健康",
          "type": "media"
        },
        {
          "name": "不想看:熊出没",
          "type": "keyword"
        },
        {
          "name": "不想看:探险",
          "type": "keyword"
        },
        {
          "name": "不想看:母婴",
          "type": "keyword"
        },
        {
          "name": "不感兴趣",
          "type": "unlike"
        }
      ],
      "isRec": 0,
      "isTop": 0,
      "keyword": "熊出没 探险 母婴",
      "mediaId": "6463053602733686785",
      "mediaName": "这里说健康",
      "newsId": "6504293370507036672",
      "picNum": 0,
      "pics": [
        {
          "height": 718,
          "url": "http://p.cdn.sohu.com/089a1b13/b4e97ca03b1adf8319c492a212a69b62",
          "width": 1280
        }
      ],
      "playCount": 3496,
      "recommendEvent": 0,
      "recpool": 0,
      "recreason": 1,
      "score": 0.2282634296178161,
      "state": 0,
      "template": 9,
      "title": "熊出没：肥猫就翻个身，强哥却掉下炕",
      "videos": [
        {
          "definitionInfos": [
            {
              "size": 3251996,
              "url": "http://v.cdn.sohu.com/93/a4432e0b62dd25469e2cfa5d7d8043e2/1"
            },
            {
              "size": 1986590,
              "url": "http://v.cdn.sohu.com/93/a4432e0b62dd25469e2cfa5d7d8043e2/0"
            }
          ],
          "duration": 51.0,
          "hd_id": 0,
          "rate": "0",
          "size": 3251996,
          "type": 0,
          "url": "http://v.cdn.sohu.com/93/a4432e0b62dd25469e2cfa5d7d8043e2/1"
        }
      ],
      "virtualTime": 1550824270747
    },
    {
      "abs": "",
      "articleUrl": "http://c.cdn.sohu.com/article/6504302015626086401",
      "category": {
        "id": 100,
        "name": "其他"
      },
      "commentNum": 0,
      "contentType": 3,
      "createTime": 1550745147,
      "filterWords": [
        {
          "name": "屏蔽来源:关心永远在",
          "type": "media"
        },
        {
          "name": "不想看:蚂蚁",
          "type": "keyword"
        },
        {
          "name": "不想看:母婴",
          "type": "keyword"
        },
        {
          "name": "不感兴趣",
          "type": "unlike"
        }
      ],
      "isRec": 0,
      "isTop": 0,
      "keyword": "蚂蚁 母婴",
      "mediaId": "6488661365199208448",
      "mediaName": "关心永远在",
      "newsId": "6504302015626086401",
      "picNum": 0,
      "pics": [
        {
          "height": 720,
          "url": "http://p.cdn.sohu.com/089a1b13/830c2681e09f0c03965c72e6d8331c29",
          "width": 1280
        }
      ],
      "playCount": 128,
      "recommendEvent": 0,
      "recpool": 0,
      "recreason": 0,
      "score": 0.11787351144347075,
      "state": 0,
      "template": 9,
      "title": "新来的幼师寥寥几笔秒画小蚂蚁，孩子们都喜欢，园长乐了",
      "videos": [
        {
          "definitionInfos": [
            {
              "size": 2027360,
              "url": "http://v.cdn.sohu.com/93/b56bf44bc3f7139149471b8101a73428/1"
            },
            {
              "size": 1013339,
              "url": "http://v.cdn.sohu.com/93/b56bf44bc3f7139149471b8101a73428/0"
            }
          ],
          "duration": 22.0,
          "hd_id": 0,
          "rate": "0",
          "size": 2027360,
          "type": 0,
          "url": "http://v.cdn.sohu.com/93/b56bf44bc3f7139149471b8101a73428/1"
        }
      ],
      "virtualTime": 1550824269810
    },
    {
      "abs": "",
      "articleUrl": "http://c.cdn.sohu.com/article/6504281290315925505",
      "category": {
        "id": 100,
        "name": "其他"
      },
      "commentNum": 0,
      "contentType": 3,
      "createTime": 1550740940,
      "filterWords": [
        {
          "name": "屏蔽来源:小米影综剧",
          "type": "media"
        },
        {
          "name": "不想看:光头强",
          "type": "keyword"
        },
        {
          "name": "不想看:母婴",
          "type": "keyword"
        },
        {
          "name": "不感兴趣",
          "type": "unlike"
        }
      ],
      "isRec": 0,
      "isTop": 0,
      "keyword": "光头强 母婴",
      "mediaId": "6502599362793701378",
      "mediaName": "小米影综剧",
      "newsId": "6504281290315925505",
      "picNum": 0,
      "pics": [
        {
          "height": 486,
          "url": "http://p.cdn.sohu.com/cdedd044/60a071027443cb2d83ec0b5bb7387d35",
          "width": 870
        }
      ],
      "playCount": 115,
      "recommendEvent": 0,
      "recpool": 0,
      "recreason": 0,
      "score": 0.11144036747250523,
      "state": 0,
      "template": 9,
      "title": "光头强到处都是，都是假的",
      "videos": [
        {
          "definitionInfos": [
            {
              "size": 3082919,
              "url": "http://v.cdn.sohu.com/0/04fede844ecc9a1a138cb90b2867dffe/0"
            }
          ],
          "duration": 57.0,
          "hd_id": 0,
          "rate": "0",
          "size": 3082919,
          "type": 0,
          "url": "http://v.cdn.sohu.com/0/04fede844ecc9a1a138cb90b2867dffe/0"
        }
      ],
      "virtualTime": 1550824268873
    },
    {
      "abs": "",
      "articleUrl": "http://c.cdn.sohu.com/article/6504013803221420033",
      "category": {
        "id": 100,
        "name": "其他"
      },
      "commentNum": 0,
      "contentType": 3,
      "createTime": 1550664337,
      "filterWords": [
        {
          "name": "屏蔽来源:不缺国度",
          "type": "media"
        },
        {
          "name": "不想看:玩具",
          "type": "keyword"
        },
        {
          "name": "不想看:模特",
          "type": "keyword"
        },
        {
          "name": "不想看:母婴",
          "type": "keyword"
        },
        {
          "name": "不感兴趣",
          "type": "unlike"
        }
      ],
      "isRec": 0,
      "isTop": 0,
      "keyword": "玩具 模特 母婴",
      "mediaId": "6490707047984660480",
      "mediaName": "不缺国度",
      "newsId": "6504013803221420033",
      "picNum": 0,
      "pics": [
        {
          "height": 486,
          "url": "http://p.cdn.sohu.com/eee85694/0a79ff2ffc323dccc2df292dcd3f273d",
          "width": 870
        }
      ],
      "playCount": 28,
      "recommendEvent": 0,
      "recpool": 0,
      "recreason": 0,
      "score": 0.08500011352877802,
      "state": 0,
      "template": 9,
      "title": "教你用旧袜子，给芭比娃娃做裙子，做法很简单",
      "videos": [
        {
          "definitionInfos": [
            {
              "size": 4780099,
              "url": "http://v.cdn.sohu.com/0/ab4874014f64dafc6abb2db6c9acf930/0"
            }
          ],
          "duration": 79.0,
          "hd_id": 0,
          "rate": "0",
          "size": 4780099,
          "type": 0,
          "url": "http://v.cdn.sohu.com/0/ab4874014f64dafc6abb2db6c9acf930/0"
        }
      ],
      "virtualTime": 1550824267936
    },
    {
      "abs": "",
      "articleUrl": "http://c.cdn.sohu.com/article/6504355103300913153",
      "category": {
        "id": 100,
        "name": "其他"
      },
      "commentNum": 0,
      "contentType": 3,
      "createTime": 1550706300,
      "filterWords": [
        {
          "name": "屏蔽来源:咩咩羊玩具",
          "type": "media"
        },
        {
          "name": "不想看:小猪佩奇",
          "type": "keyword"
        },
        {
          "name": "不想看:母婴",
          "type": "keyword"
        },
        {
          "name": "不感兴趣",
          "type": "unlike"
        }
      ],
      "isRec": 0,
      "isTop": 0,
      "keyword": "小猪佩奇 母婴",
      "mediaId": "6472703347743784960",
      "mediaName": "咩咩羊玩具",
      "newsId": "6504355103300913153",
      "picNum": 0,
      "pics": [
        {
          "height": 486,
          "url": "http://p.cdn.sohu.com/eee85694/ceec50e8fdedca7bb0162004863adcb4",
          "width": 870
        }
      ],
      "playCount": 11,
      "recommendEvent": 0,
      "recpool": 0,
      "recreason": 0,
      "score": 0.08180846739094923,
      "state": 0,
      "template": 9,
      "title": "太美味！小猪佩奇做出什么好吃的东西呢？竟然吃得满嘴都是？",
      "videos": [
        {
          "definitionInfos": [
            {
              "size": 4123448,
              "url": "http://v.cdn.sohu.com/0/1ef83fc9ef616276639f4eca373d54dc/0"
            }
          ],
          "duration": 81.0,
          "hd_id": 0,
          "rate": "0",
          "size": 4123448,
          "type": 0,
          "url": "http://v.cdn.sohu.com/0/1ef83fc9ef616276639f4eca373d54dc/0"
        }
      ],
      "virtualTime": 1550824266999
    },
    {
      "abs": "",
      "articleUrl": "http://c.cdn.sohu.com/article/6504006853842700289",
      "category": {
        "id": 100,
        "name": "其他"
      },
      "commentNum": 0,
      "contentType": 3,
      "createTime": 1550627640,
      "filterWords": [
        {
          "name": "屏蔽来源:情缘夜里",
          "type": "media"
        },
        {
          "name": "不想看:奥特曼",
          "type": "keyword"
        },
        {
          "name": "不想看:杰顿",
          "type": "keyword"
        },
        {
          "name": "不想看:母婴",
          "type": "keyword"
        },
        {
          "name": "不感兴趣",
          "type": "unlike"
        }
      ],
      "isRec": 0,
      "isTop": 0,
      "keyword": "奥特曼 杰顿 母婴",
      "mediaId": "6457097790307696641",
      "mediaName": "情缘夜里",
      "newsId": "6504006853842700289",
      "picNum": 0,
      "pics": [
        {
          "height": 486,
          "url": "http://p.cdn.sohu.com/cdedd044/0f060ecefa08da62894b3748f1a6cb38",
          "width": 870
        }
      ],
      "playCount": 21,
      "recommendEvent": 0,
      "recpool": 0,
      "recreason": 0,
      "score": 0.05016943041328694,
      "state": 0,
      "template": 9,
      "title": "奥特曼为了得到怪兽杰顿的力量，答应和杰顿合作杀掉奥特曼队友",
      "videos": [
        {
          "definitionInfos": [
            {
              "size": 1295028,
              "url": "http://v.cdn.sohu.com/0/44801f938002e6d08dba76898c7bff00/0"
            }
          ],
          "duration": 17.0,
          "hd_id": 0,
          "rate": "0",
          "size": 1295028,
          "type": 0,
          "url": "http://v.cdn.sohu.com/0/44801f938002e6d08dba76898c7bff00/0"
        }
      ],
      "virtualTime": 1550824266062
    },
    {
      "abs": "",
      "articleUrl": "http://c.cdn.sohu.com/article/6503961009189816321",
      "category": {
        "id": 100,
        "name": "其他"
      },
      "commentNum": 0,
      "contentType": 3,
      "createTime": 1550660686,
      "filterWords": [
        {
          "name": "屏蔽来源:星光漫漫天",
          "type": "media"
        },
        {
          "name": "不想看:奥特曼",
          "type": "keyword"
        },
        {
          "name": "不想看:动漫",
          "type": "keyword"
        },
        {
          "name": "不想看:母婴",
          "type": "keyword"
        },
        {
          "name": "不感兴趣",
          "type": "unlike"
        }
      ],
      "isRec": 0,
      "isTop": 0,
      "keyword": "奥特曼 动漫 母婴",
      "mediaId": "6445645342598758400",
      "mediaName": "星光漫漫天",
      "newsId": "6503961009189816321",
      "picNum": 0,
      "pics": [
        {
          "height": 486,
          "url": "http://p.cdn.sohu.com/eee85694/db1e182ea37bbc45f16635e460c00e8a",
          "width": 870
        }
      ],
      "playCount": 77,
      "recommendEvent": 0,
      "recpool": 0,
      "recreason": 0,
      "score": 0.04898351910673403,
      "state": 0,
      "template": 9,
      "title": "还有这种操作？怪兽帮着奥特曼攻击自己的同伴",
      "videos": [
        {
          "definitionInfos": [
            {
              "size": 6858200,
              "url": "http://v.cdn.sohu.com/0/c27986fdd3b95d36106b826ea596c036/0"
            }
          ],
          "duration": 78.0,
          "hd_id": 0,
          "rate": "0",
          "size": 6858200,
          "type": 0,
          "url": "http://v.cdn.sohu.com/0/c27986fdd3b95d36106b826ea596c036/0"
        }
      ],
      "virtualTime": 1550824265125
    },
    {
      "abs": "",
      "articleUrl": "http://c.cdn.sohu.com/article/6503881909506934785",
      "category": {
        "id": 100,
        "name": "其他"
      },
      "commentNum": 0,
      "contentType": 3,
      "createTime": 1550645045,
      "filterWords": [
        {
          "name": "屏蔽来源:小明爱动漫",
          "type": "media"
        },
        {
          "name": "不想看:英语",
          "type": "keyword"
        },
        {
          "name": "不想看:益智",
          "type": "keyword"
        },
        {
          "name": "不想看:母婴",
          "type": "keyword"
        },
        {
          "name": "不感兴趣",
          "type": "unlike"
        }
      ],
      "isRec": 0,
      "isTop": 0,
      "keyword": "英语 益智 母婴",
      "mediaId": "6488298880873005058",
      "mediaName": "小明爱动漫",
      "newsId": "6503881909506934785",
      "picNum": 0,
      "pics": [
        {
          "height": 360,
          "url": "http://p.cdn.sohu.com/089a1b13/ae15cb781edbea755747bf1a641e46df",
          "width": 640
        }
      ],
      "playCount": 20,
      "recommendEvent": 0,
      "recpool": 0,
      "recreason": 0,
      "score": 0.04662735474296816,
      "state": 0,
      "template": 9,
      "title": "英语益智动漫：宝宝爱吃土豆，大家一起吃土豆泥，还能学习知识",
      "videos": [
        {
          "definitionInfos": [
            {
              "size": 8182047,
              "url": "http://v.cdn.sohu.com/93/5529afe7823e278303aeaa836cc2a1cf/0"
            },
            {
              "size": 6646705,
              "url": "http://v.cdn.sohu.com/93/5529afe7823e278303aeaa836cc2a1cf/1"
            }
          ],
          "duration": 114.0,
          "hd_id": 0,
          "rate": "0",
          "size": 8182047,
          "type": 0,
          "url": "http://v.cdn.sohu.com/93/5529afe7823e278303aeaa836cc2a1cf/0"
        }
      ],
      "virtualTime": 1550824264188
    },
    {
      "abs": "",
      "articleUrl": "http://c.cdn.sohu.com/article/6503848786534598656",
      "category": {
        "id": 100,
        "name": "其他"
      },
      "commentNum": 0,
      "contentType": 3,
      "createTime": 1550637206,
      "filterWords": [
        {
          "name": "屏蔽来源:婴幼儿食谱",
          "type": "media"
        },
        {
          "name": "不想看:动物",
          "type": "keyword"
        },
        {
          "name": "不想看:蟒蛇",
          "type": "keyword"
        },
        {
          "name": "不想看:母婴",
          "type": "keyword"
        },
        {
          "name": "不感兴趣",
          "type": "unlike"
        }
      ],
      "isRec": 0,
      "isTop": 0,
      "keyword": "动物 蟒蛇 母婴",
      "mediaId": "6463053009168367616",
      "mediaName": "婴幼儿食谱",
      "newsId": "6503848786534598656",
      "picNum": 0,
      "pics": [
        {
          "height": 718,
          "url": "http://p.cdn.sohu.com/089a1b13/67f657426cfa4486de000dce8a4f54d5",
          "width": 1280
        }
      ],
      "playCount": 22,
      "recommendEvent": 0,
      "recpool": 0,
      "recreason": 0,
      "score": 0.04458758995629538,
      "state": 0,
      "template": 9,
      "title": "蟒蛇经过彩色喷泉后变了颜色，认识动物",
      "videos": [
        {
          "definitionInfos": [
            {
              "size": 11347880,
              "url": "http://v.cdn.sohu.com/93/c4d15739fde1bf0edd54749f75555cb2/1"
            },
            {
              "size": 5325975,
              "url": "http://v.cdn.sohu.com/93/c4d15739fde1bf0edd54749f75555cb2/0"
            }
          ],
          "duration": 78.0,
          "hd_id": 0,
          "rate": "0",
          "size": 11347880,
          "type": 0,
          "url": "http://v.cdn.sohu.com/93/c4d15739fde1bf0edd54749f75555cb2/1"
        }
      ],
      "virtualTime": 1550824263251
    },
    {
      "abs": "",
      "articleUrl": "http://c.cdn.sohu.com/article/6504174136804247553",
      "category": {
        "id": 100,
        "name": "其他"
      },
      "commentNum": 0,
      "contentType": 3,
      "createTime": 1550705880,
      "filterWords": [
        {
          "name": "屏蔽来源:金州欢乐玩具乐园",
          "type": "media"
        },
        {
          "name": "不想看:玛格",
          "type": "keyword"
        },
        {
          "name": "不想看:奥特曼",
          "type": "keyword"
        },
        {
          "name": "不想看:母婴",
          "type": "keyword"
        },
        {
          "name": "不感兴趣",
          "type": "unlike"
        }
      ],
      "isRec": 0,
      "isTop": 0,
      "keyword": "玛格 奥特曼 母婴",
      "mediaId": "6491866580454998016",
      "mediaName": "金州欢乐玩具乐园",
      "newsId": "6504174136804247553",
      "picNum": 0,
      "pics": [
        {
          "height": 474,
          "url": "http://p.cdn.sohu.com/cdedd044/e06754c917efeb707ce9fc3645f43f46",
          "width": 848
        }
      ],
      "playCount": 14,
      "recommendEvent": 0,
      "recpool": 0,
      "recreason": 0,
      "score": 0.03833083418416944,
      "state": 0,
      "template": 9,
      "title": "捷德奥特曼豪勇形态释放光波对付玛格大蛇怪兽",
      "videos": [
        {
          "definitionInfos": [
            {
              "size": 3029929,
              "url": "http://v.cdn.sohu.com/0/3d110809166ce7fd57dade8b30ba9ec7/0"
            }
          ],
          "duration": 59.0,
          "hd_id": 0,
          "rate": "0",
          "size": 3029929,
          "type": 0,
          "url": "http://v.cdn.sohu.com/0/3d110809166ce7fd57dade8b30ba9ec7/0"
        }
      ],
      "virtualTime": 1550824262314
    },
    {
      "abs": "",
      "articleUrl": "http://c.cdn.sohu.com/article/6504472269723535361",
      "category": {
        "id": 100,
        "name": "其他"
      },
      "commentNum": 0,
      "contentType": 3,
      "createTime": 1550786603,
      "filterWords": [
        {
          "name": "屏蔽来源:松松贝拉",
          "type": "media"
        },
        {
          "name": "不想看:足球",
          "type": "keyword"
        },
        {
          "name": "不想看:中国足球",
          "type": "keyword"
        },
        {
          "name": "不想看:母婴",
          "type": "keyword"
        },
        {
          "name": "不感兴趣",
          "type": "unlike"
        }
      ],
      "isRec": 0,
      "isTop": 0,
      "keyword": "足球 中国足球 母婴",
      "mediaId": "6463052923088666624",
      "mediaName": "松松贝拉",
      "newsId": "6504472269723535361",
      "picNum": 0,
      "pics": [
        {
          "height": 494,
          "url": "http://p.cdn.sohu.com/089a1b13/9109fd9ba38a0879a7f33819f46882b6",
          "width": 880
        }
      ],
      "playCount": 1100,
      "recommendEvent": 0,
      "recpool": 0,
      "recreason": 1,
      "score": 0.1835292476159802,
      "state": 0,
      "template": 9,
      "title": "吃豆人咬碎了不同颜色的足球改变了颜色，少儿双语",
      "videos": [
        {
          "definitionInfos": [
            {
              "size": 14796233,
              "url": "http://v.cdn.sohu.com/93/04b59a4875fe9b89d2c1f1419c8f90cc/1"
            },
            {
              "size": 7443283,
              "url": "http://v.cdn.sohu.com/93/04b59a4875fe9b89d2c1f1419c8f90cc/0"
            }
          ],
          "duration": 125.0,
          "hd_id": 0,
          "rate": "0",
          "size": 14796233,
          "type": 0,
          "url": "http://v.cdn.sohu.com/93/04b59a4875fe9b89d2c1f1419c8f90cc/1"
        }
      ],
      "virtualTime": 1550824312017
    },
    {
      "abs": "",
      "articleUrl": "http://c.cdn.sohu.com/article/6504515092254558209",
      "category": {
        "id": 100,
        "name": "其他"
      },
      "commentNum": 0,
      "contentType": 3,
      "createTime": 1550795460,
      "filterWords": [
        {
          "name": "屏蔽来源:辰宝早教屋",
          "type": "media"
        },
        {
          "name": "不想看:乔治",
          "type": "keyword"
        },
        {
          "name": "不想看:游艇",
          "type": "keyword"
        },
        {
          "name": "不想看:母婴",
          "type": "keyword"
        },
        {
          "name": "不感兴趣",
          "type": "unlike"
        }
      ],
      "isRec": 0,
      "isTop": 0,
      "keyword": "乔治 游艇 母婴",
      "mediaId": "6430336171015929857",
      "mediaName": "辰宝早教屋",
      "newsId": "6504515092254558209",
      "picNum": 0,
      "pics": [
        {
          "height": 720,
          "url": "http://p.cdn.sohu.com/089a1b13/15c64fbe1402724c7179f899e1dc7274",
          "width": 1280
        }
      ],
      "playCount": 78,
      "recommendEvent": 0,
      "recpool": 0,
      "recreason": 1,
      "score": 0.1653968799462741,
      "state": 0,
      "template": 9,
      "title": "小猪佩奇：猪爸爸带佩奇和乔治跳泥坑吹泡泡！",
      "videos": [
        {
          "definitionInfos": [
            {
              "size": 2572245,
              "url": "http://v.cdn.sohu.com/93/4882e3f13127410f48561e9ea5aa6e29/0"
            },
            {
              "size": 1892816,
              "url": "http://v.cdn.sohu.com/93/4882e3f13127410f48561e9ea5aa6e29/1"
            }
          ],
          "duration": 64.0,
          "hd_id": 0,
          "rate": "0",
          "size": 2572245,
          "type": 0,
          "url": "http://v.cdn.sohu.com/93/4882e3f13127410f48561e9ea5aa6e29/0"
        }
      ],
      "virtualTime": 1550824310490
    },
    {
      "abs": "",
      "articleUrl": "http://c.cdn.sohu.com/article/6504342487149053952",
      "category": {
        "id": 100,
        "name": "其他"
      },
      "commentNum": 0,
      "contentType": 3,
      "createTime": 1550753370,
      "filterWords": [
        {
          "name": "屏蔽来源:以南妈妈育儿",
          "type": "media"
        },
        {
          "name": "不想看:赵琳",
          "type": "keyword"
        },
        {
          "name": "不想看:熊出没",
          "type": "keyword"
        },
        {
          "name": "不想看:母婴",
          "type": "keyword"
        },
        {
          "name": "不感兴趣",
          "type": "unlike"
        }
      ],
      "isRec": 0,
      "isTop": 0,
      "keyword": "赵琳 熊出没 母婴",
      "mediaId": "6463053473096138753",
      "mediaName": "以南妈妈育儿",
      "newsId": "6504342487149053952",
      "picNum": 0,
      "pics": [
        {
          "height": 1077,
          "url": "http://p.cdn.sohu.com/089a1b13/9dfc236f4ec91580d3b4c9d7bf8203b5",
          "width": 1920
        }
      ],
      "playCount": 204,
      "recommendEvent": 0,
      "recpool": 0,
      "recreason": 1,
      "score": 0.14205673302869984,
      "state": 0,
      "template": 9,
      "title": "熊出没：赵琳在野外撒欢，还追兔子，兔子找你惹你了",
      "videos": [
        {
          "definitionInfos": [
            {
              "size": 7103940,
              "url": "http://v.cdn.sohu.com/93/f77544292cca4c15ed5bf7b3b9dff6ed/0"
            },
            {
              "size": 2954198,
              "url": "http://v.cdn.sohu.com/93/f77544292cca4c15ed5bf7b3b9dff6ed/1"
            }
          ],
          "duration": 54.0,
          "hd_id": 0,
          "rate": "0",
          "size": 7103940,
          "type": 0,
          "url": "http://v.cdn.sohu.com/93/f77544292cca4c15ed5bf7b3b9dff6ed/0"
        }
      ],
      "virtualTime": 1550824308963
    },
    {
      "abs": "",
      "articleUrl": "http://c.cdn.sohu.com/article/6504328296568719360",
      "category": {
        "id": 100,
        "name": "其他"
      },
      "commentNum": 0,
      "contentType": 3,
      "createTime": 1550743120,
      "filterWords": [
        {
          "name": "屏蔽来源:原始动漫",
          "type": "media"
        },
        {
          "name": "不想看:凯伦",
          "type": "keyword"
        },
        {
          "name": "不想看:海绵宝宝",
          "type": "keyword"
        },
        {
          "name": "不想看:母婴",
          "type": "keyword"
        },
        {
          "name": "不感兴趣",
          "type": "unlike"
        }
      ],
      "isRec": 0,
      "isTop": 0,
      "keyword": "凯伦 海绵宝宝 母婴",
      "mediaId": "6463546277064867840",
      "mediaName": "原始动漫",
      "newsId": "6504328296568719360",
      "picNum": 0,
      "pics": [
        {
          "height": 358,
          "url": "http://p.cdn.sohu.com/eee85694/37e3dc01cf601f10011a61db752a0bb2",
          "width": 640
        }
      ],
      "playCount": 84,
      "recommendEvent": 0,
      "recpool": 0,
      "recreason": 0,
      "score": 0.09801311107252353,
      "state": 0,
      "template": 9,
      "title": "海绵宝宝在凯伦心里的形象原来是个正方体，这也太方了吧",
      "videos": [
        {
          "definitionInfos": [
            {
              "size": 1968138,
              "url": "http://v.cdn.sohu.com/0/1b3b476ab26fce26a51ae2eb092fe56c/0"
            }
          ],
          "duration": 36.0,
          "hd_id": 0,
          "rate": "0",
          "size": 1968138,
          "type": 0,
          "url": "http://v.cdn.sohu.com/0/1b3b476ab26fce26a51ae2eb092fe56c/0"
        }
      ],
      "virtualTime": 1550824307436
    },
    {
      "abs": "",
      "articleUrl": "http://c.cdn.sohu.com/article/6503895845736286209",
      "category": {
        "id": 100,
        "name": "其他"
      },
      "commentNum": 0,
      "contentType": 3,
      "createTime": 1550638171,
      "filterWords": [
        {
          "name": "屏蔽来源:甜甜影视汇",
          "type": "media"
        },
        {
          "name": "不想看:熊出没",
          "type": "keyword"
        },
        {
          "name": "不想看:动画电影",
          "type": "keyword"
        },
        {
          "name": "不想看:母婴",
          "type": "keyword"
        },
        {
          "name": "不感兴趣",
          "type": "unlike"
        }
      ],
      "isRec": 0,
      "isTop": 0,
      "keyword": "熊出没 动画电影 母婴",
      "mediaId": "6496264165827543041",
      "mediaName": "甜甜影视汇",
      "newsId": "6503895845736286209",
      "picNum": 0,
      "pics": [
        {
          "height": 483,
          "url": "http://p.cdn.sohu.com/eee85694/b8a79881766af91f335f1b507a2258c2",
          "width": 864
        }
      ],
      "playCount": 334,
      "recommendEvent": 0,
      "recpool": 0,
      "recreason": 0,
      "score": 0.09113933129689833,
      "state": 0,
      "template": 9,
      "title": "熊出没：涂涂以为自己飞不起来开始哭了熊妈妈回来了这下有办法了",
      "videos": [
        {
          "definitionInfos": [
            {
              "size": 2763174,
              "url": "http://v.cdn.sohu.com/0/008d76eb0b1320e7a110d76b0dfd82fe/0"
            }
          ],
          "duration": 38.0,
          "hd_id": 0,
          "rate": "0",
          "size": 2763174,
          "type": 0,
          "url": "http://v.cdn.sohu.com/0/008d76eb0b1320e7a110d76b0dfd82fe/0"
        }
      ],
      "virtualTime": 1550824305909
    },
    {
      "abs": "",
      "articleUrl": "http://c.cdn.sohu.com/article/6503842328493426688",
      "category": {
        "id": 100,
        "name": "其他"
      },
      "commentNum": 0,
      "contentType": 3,
      "createTime": 1550619000,
      "filterWords": [
        {
          "name": "屏蔽来源:咩咩羊玩具",
          "type": "media"
        },
        {
          "name": "不想看:乔治",
          "type": "keyword"
        },
        {
          "name": "不想看:草莓",
          "type": "keyword"
        },
        {
          "name": "不想看:母婴",
          "type": "keyword"
        },
        {
          "name": "不感兴趣",
          "type": "unlike"
        }
      ],
      "isRec": 0,
      "isTop": 0,
      "keyword": "乔治 草莓 母婴",
      "mediaId": "6472703347743784960",
      "mediaName": "咩咩羊玩具",
      "newsId": "6503842328493426688",
      "picNum": 0,
      "pics": [
        {
          "height": 486,
          "url": "http://p.cdn.sohu.com/eee85694/c056580dda559038b8bccd321d221b99",
          "width": 870
        }
      ],
      "playCount": 112,
      "recommendEvent": 0,
      "recpool": 0,
      "recreason": 0,
      "score": 0.07583632709539855,
      "state": 0,
      "template": 9,
      "title": "超好吃！小猪佩奇和乔治怎么吃掉这么多大草莓蛋糕呢？猪妈妈呢？",
      "videos": [
        {
          "definitionInfos": [
            {
              "size": 3685431,
              "url": "http://v.cdn.sohu.com/0/eef6b3ef8e715897fc042ff0280d7246/0"
            }
          ],
          "duration": 69.0,
          "hd_id": 0,
          "rate": "0",
          "size": 3685431,
          "type": 0,
          "url": "http://v.cdn.sohu.com/0/eef6b3ef8e715897fc042ff0280d7246/0"
        }
      ],
      "virtualTime": 1550824304382
    },
    {
      "abs": "",
      "articleUrl": "http://c.cdn.sohu.com/article/6504337573492557825",
      "category": {
        "id": 100,
        "name": "其他"
      },
      "commentNum": 60,
      "contentType": 3,
      "createTime": 1550733932,
      "filterWords": [
        {
          "name": "屏蔽来源:鱼妈手作",
          "type": "media"
        },
        {
          "name": "不想看:水果",
          "type": "keyword"
        },
        {
          "name": "不想看:护肤",
          "type": "keyword"
        },
        {
          "name": "不想看:母婴",
          "type": "keyword"
        },
        {
          "name": "不感兴趣",
          "type": "unlike"
        }
      ],
      "isRec": 0,
      "isTop": 0,
      "keyword": "水果 护肤 母婴",
      "mediaId": "6447561288590557184",
      "mediaName": "鱼妈手作",
      "newsId": "6504337573492557825",
      "picNum": 0,
      "pics": [
        {
          "height": 486,
          "url": "http://p.cdn.sohu.com/eee85694/6abf7142565bf760eb092c3c41d35dfc",
          "width": 870
        }
      ],
      "playCount": 37,
      "recommendEvent": 0,
      "recpool": 0,
      "recreason": 0,
      "score": 0.07559750256020473,
      "state": 0,
      "template": 9,
      "title": "挑战火龙果洗泥，无硼砂无胶水，实在太过瘾啦！结局很惊喜",
      "videos": [
        {
          "definitionInfos": [
            {
              "size": 8888617,
              "url": "http://v.cdn.sohu.com/0/341a1247e8f28e6001ac4dd7031b2473/0"
            }
          ],
          "duration": 73.0,
          "hd_id": 0,
          "rate": "0",
          "size": 8888617,
          "type": 0,
          "url": "http://v.cdn.sohu.com/0/341a1247e8f28e6001ac4dd7031b2473/0"
        }
      ],
      "virtualTime": 1550824302855
    },
    {
      "abs": "",
      "articleUrl": "http://c.cdn.sohu.com/article/6503943697359439872",
      "category": {
        "id": 100,
        "name": "其他"
      },
      "commentNum": 0,
      "contentType": 3,
      "createTime": 1550651526,
      "filterWords": [
        {
          "name": "屏蔽来源:晓童玩具",
          "type": "media"
        },
        {
          "name": "不想看:奥特曼",
          "type": "keyword"
        },
        {
          "name": "不想看:宇宙",
          "type": "keyword"
        },
        {
          "name": "不想看:母婴",
          "type": "keyword"
        },
        {
          "name": "不感兴趣",
          "type": "unlike"
        }
      ],
      "isRec": 0,
      "isTop": 0,
      "keyword": "奥特曼 宇宙 母婴",
      "mediaId": "6445663920425271297",
      "mediaName": "晓童玩具",
      "newsId": "6503943697359439872",
      "picNum": 0,
      "pics": [
        {
          "height": 1008,
          "url": "http://p.cdn.sohu.com/covers/089a1b13/31f4a973dd7ca74cdc63a83f98e8b74f.jpeg",
          "width": 1800
        }
      ],
      "playCount": 14,
      "recommendEvent": 0,
      "recpool": 0,
      "recreason": 0,
      "score": 0.04170038133826463,
      "state": 0,
      "template": 9,
      "title": "奥特曼玩具！黑暗欧布用罗布水晶召唤奥特曼怪兽大作战！",
      "videos": [
        {
          "definitionInfos": [
            {
              "size": 26479994,
              "url": "http://v.cdn.sohu.com/93/638fbc89f77deeddecb8f9ab4fcf98e8/1"
            },
            {
              "size": 14287490,
              "url": "http://v.cdn.sohu.com/93/638fbc89f77deeddecb8f9ab4fcf98e8/0"
            }
          ],
          "duration": 344.0,
          "hd_id": 0,
          "rate": "0",
          "size": 26479994,
          "type": 0,
          "url": "http://v.cdn.sohu.com/93/638fbc89f77deeddecb8f9ab4fcf98e8/1"
        }
      ],
      "virtualTime": 1550824301328
    },
    {
      "abs": "",
      "articleUrl": "http://c.cdn.sohu.com/article/6504576788864174080",
      "category": {
        "id": 100,
        "name": "其他"
      },
      "commentNum": 0,
      "contentType": 3,
      "createTime": 1550809173,
      "filterWords": [
        {
          "name": "屏蔽来源:育儿纪录者",
          "type": "media"
        },
        {
          "name": "不想看:早教",
          "type": "keyword"
        },
        {
          "name": "不想看:烹饪技巧",
          "type": "keyword"
        },
        {
          "name": "不想看:母婴",
          "type": "keyword"
        },
        {
          "name": "不感兴趣",
          "type": "unlike"
        }
      ],
      "isRec": 0,
      "isTop": 0,
      "keyword": "早教 烹饪技巧 母婴",
      "mediaId": "6463053630567088131",
      "mediaName": "育儿纪录者",
      "newsId": "6504576788864174080",
      "picNum": 0,
      "pics": [
        {
          "height": 360,
          "url": "http://p.cdn.sohu.com/089a1b13/9048e1913415de7797ab23a4903e59fe",
          "width": 640
        }
      ],
      "playCount": 3,
      "recommendEvent": 0,
      "recpool": 0,
      "recreason": 0,
      "score": 0.041250530142161186,
      "state": 0,
      "template": 9,
      "title": "儿童切切乐早教玩具：红辣椒柠檬玉米大葱土豆美味集合",
      "videos": [
        {
          "definitionInfos": [
            {
              "size": 20686760,
              "url": "http://v.cdn.sohu.com/93/113eb588df8b64fc5303b05bb5676550/0"
            },
            {
              "size": 18399599,
              "url": "http://v.cdn.sohu.com/93/113eb588df8b64fc5303b05bb5676550/1"
            }
          ],
          "duration": 430.0,
          "hd_id": 0,
          "rate": "0",
          "size": 20686760,
          "type": 0,
          "url": "http://v.cdn.sohu.com/93/113eb588df8b64fc5303b05bb5676550/0"
        }
      ],
      "virtualTime": 1550824299801
    },
    {
      "abs": "",
      "articleUrl": "http://c.cdn.sohu.com/article/6504579579548534785",
      "category": {
        "id": 100,
        "name": "其他"
      },
      "commentNum": 0,
      "contentType": 3,
      "createTime": 1550592300,
      "filterWords": [
        {
          "name": "屏蔽来源:小文教你学手工",
          "type": "media"
        },
        {
          "name": "不想看:蛇",
          "type": "keyword"
        },
        {
          "name": "不想看:蟾蜍",
          "type": "keyword"
        },
        {
          "name": "不想看:母婴",
          "type": "keyword"
        },
        {
          "name": "不感兴趣",
          "type": "unlike"
        }
      ],
      "isRec": 0,
      "isTop": 0,
      "keyword": "蛇 蟾蜍 母婴",
      "mediaId": "6483999075795468301",
      "mediaName": "小文教你学手工",
      "newsId": "6504579579548534785",
      "picNum": 0,
      "pics": [
        {
          "height": 444,
          "url": "http://p.cdn.sohu.com/03f6845a/e9928acf78c64863d7fa05ee8b69c446",
          "width": 960
        }
      ],
      "playCount": 0,
      "recommendEvent": 0,
      "recpool": 0,
      "recreason": 0,
      "score": 0.018850407483796395,
      "state": 0,
      "template": 9,
      "title": "迷你特工队：王子先行撤离，特工队与蛇巫决一死战！",
      "videos": [
        {
          "definitionInfos": [
            {
              "size": 9427993,
              "url": "http://v.cdn.sohu.com/14/2523ae920a72e546665d847045fa2782"
            }
          ],
          "duration": 224.0,
          "hd_id": 0,
          "rate": "0",
          "size": 9427993,
          "type": 0,
          "url": "http://v.cdn.sohu.com/14/2523ae920a72e546665d847045fa2782"
        }
      ],
      "virtualTime": 1550824298274
    },
    {
      "template": 9,
      "mediaId": "6187459208384872449",
      "recreason": 1,
      "createTime": 1550768363,
      "recommendEvent": 0,
      "virtualTime": 1550824245411,
      "videos": [
        {
          "duration": 22.0,
          "hd_id": 0,
          "rate": "0",
          "definitionInfos": [
            {
              "url": "http://v.cdn.sohu.com/93/07371d13c3770d91412d5688721bd6a6/0",
              "size": 3467958
            },
            {
              "url": "http://v.cdn.sohu.com/93/07371d13c3770d91412d5688721bd6a6/1",
              "size": 1313527
            }
          ],
          "type": 0,
          "url": "http://v.cdn.sohu.com/93/07371d13c3770d91412d5688721bd6a6/0",
          "size": 3467958
        }
      ],
      "keyword": "生肖 母婴",
      "score": 0.2649238230296173,
      "mediaName": "美拍",
      "state": 0,
      "isRec": 0,
      "contentType": 3,
      "picNum": 0,
      "articleUrl": "http://c.cdn.sohu.com/article/6504394368869206017",
      "commentNum": 0,
      "filterWords": [
        {
          "name": "屏蔽来源:美拍",
          "type": "media"
        },
        {
          "name": "不想看:生肖",
          "type": "keyword"
        },
        {
          "name": "不想看:母婴",
          "type": "keyword"
        },
        {
          "name": "不感兴趣",
          "type": "unlike"
        }
      ],
      "pics": [
        {
          "height": 164,
          "width": 339,
          "url": "http://p.cdn.sohu.com/covers/089a1b13/3461ce695a675b7806aeea708a800c34.jpeg"
        }
      ],
      "title": "猛虎，萌虎，傻傻分不清楚",
      "category": {
        "id": 100,
        "name": "其他"
      },
      "newsId": "6504394368869206017",
      "abs": "",
      "playCount": 16451,
      "recpool": 0,
      "isTop": 0
    },
    {
      "template": 9,
      "mediaId": "6464174961631166465",
      "recreason": 0,
      "createTime": 1550807380,
      "recommendEvent": 0,
      "virtualTime": 1550824178745,
      "videos": [
        {
          "duration": 29.0,
          "hd_id": 0,
          "rate": "0",
          "definitionInfos": [
            {
              "url": "http://v.cdn.sohu.com/93/b86fabbf8c58497046f84a72f50f7bf5/0",
              "size": 1628782
            },
            {
              "url": "http://v.cdn.sohu.com/93/b86fabbf8c58497046f84a72f50f7bf5/1",
              "size": 998489
            }
          ],
          "type": 0,
          "url": "http://v.cdn.sohu.com/93/b86fabbf8c58497046f84a72f50f7bf5/0",
          "size": 1628782
        }
      ],
      "keyword": "冰淇淋 甜品 母婴",
      "score": 0.16056966242175313,
      "mediaName": "猫哥电影娱乐",
      "state": 0,
      "isRec": 0,
      "contentType": 3,
      "picNum": 0,
      "articleUrl": "http://c.cdn.sohu.com/article/6504561798623004672",
      "commentNum": 0,
      "filterWords": [
        {
          "name": "屏蔽来源:猫哥电影娱乐",
          "type": "media"
        },
        {
          "name": "不想看:冰淇淋",
          "type": "keyword"
        },
        {
          "name": "不想看:甜品",
          "type": "keyword"
        },
        {
          "name": "不想看:母婴",
          "type": "keyword"
        },
        {
          "name": "不感兴趣",
          "type": "unlike"
        }
      ],
      "pics": [
        {
          "height": 720,
          "width": 1280,
          "url": "http://p.cdn.sohu.com/089a1b13/1b2a6bbf6f5d05ded9e6d13e24e29568"
        }
      ],
      "title": "美味的冰淇凌加上果酱更好次",
      "category": {
        "id": 100,
        "name": "其他"
      },
      "newsId": "6504561798623004672",
      "abs": "",
      "playCount": 36,
      "recpool": 0,
      "isTop": 0
    },
    {
      "template": 9,
      "mediaId": "6187459208384872449",
      "recreason": 0,
      "createTime": 1550767460,
      "recommendEvent": 0,
      "virtualTime": 1550824112079,
      "videos": [
        {
          "duration": 34.0,
          "hd_id": 0,
          "rate": "0",
          "definitionInfos": [
            {
              "url": "http://v.cdn.sohu.com/93/1fcfb53b3c0560825a31659a848e26db/0",
              "size": 3884007
            },
            {
              "url": "http://v.cdn.sohu.com/93/1fcfb53b3c0560825a31659a848e26db/1",
              "size": 2489198
            }
          ],
          "type": 0,
          "url": "http://v.cdn.sohu.com/93/1fcfb53b3c0560825a31659a848e26db/0",
          "size": 3884007
        }
      ],
      "keyword": "日本 北海道 母婴",
      "score": 0.1477850325013731,
      "mediaName": "美拍",
      "state": 0,
      "isRec": 0,
      "contentType": 3,
      "picNum": 0,
      "articleUrl": "http://c.cdn.sohu.com/article/6504395415717152769",
      "commentNum": 0,
      "filterWords": [
        {
          "name": "屏蔽来源:美拍",
          "type": "media"
        },
        {
          "name": "不想看:日本",
          "type": "keyword"
        },
        {
          "name": "不想看:北海道",
          "type": "keyword"
        },
        {
          "name": "不想看:母婴",
          "type": "keyword"
        },
        {
          "name": "不感兴趣",
          "type": "unlike"
        }
      ],
      "pics": [
        {
          "height": 540,
          "width": 960,
          "url": "http://p.cdn.sohu.com/089a1b13/6ad8bb534c34c7f151ca264471cd135a"
        }
      ],
      "title": "企鹅寿司盲盒拆到隐藏款啦",
      "category": {
        "id": 100,
        "name": "其他"
      },
      "newsId": "6504395415717152769",
      "abs": "",
      "playCount": 405,
      "recpool": 0,
      "isTop": 0
    },
    {
      "template": 9,
      "mediaId": "6501375316659798017",
      "recreason": 0,
      "createTime": 1550794016,
      "recommendEvent": 0,
      "virtualTime": 1550824045413,
      "videos": [
        {
          "duration": 31.0,
          "hd_id": 0,
          "rate": "0",
          "definitionInfos": [
            {
              "url": "http://v.cdn.sohu.com/93/910579875ddb0f5ca9713a295c9e9317/0",
              "size": 1066811
            },
            {
              "url": "http://v.cdn.sohu.com/93/910579875ddb0f5ca9713a295c9e9317/1",
              "size": 864400
            }
          ],
          "type": 0,
          "url": "http://v.cdn.sohu.com/93/910579875ddb0f5ca9713a295c9e9317/0",
          "size": 1066811
        }
      ],
      "keyword": "海绵宝宝 欧美动漫 母婴",
      "score": 0.13185060327948792,
      "mediaName": "洋葱模糊了眼",
      "state": 0,
      "isRec": 0,
      "contentType": 3,
      "picNum": 0,
      "articleUrl": "http://c.cdn.sohu.com/article/6504515308475123713",
      "commentNum": 0,
      "filterWords": [
        {
          "name": "屏蔽来源:洋葱模糊了眼",
          "type": "media"
        },
        {
          "name": "不想看:海绵宝宝",
          "type": "keyword"
        },
        {
          "name": "不想看:欧美动漫",
          "type": "keyword"
        },
        {
          "name": "不想看:母婴",
          "type": "keyword"
        },
        {
          "name": "不感兴趣",
          "type": "unlike"
        }
      ],
      "pics": [
        {
          "height": 450,
          "width": 800,
          "url": "http://p.cdn.sohu.com/covers/089a1b13/737ac2ffc7c78d1d5b5d23953727d931.jpeg"
        }
      ],
      "title": "海绵宝宝拼图：海绵宝宝好惊讶，蟹老板为了他，拒绝他的三个外甥",
      "category": {
        "id": 100,
        "name": "其他"
      },
      "newsId": "6504515308475123713",
      "abs": "",
      "playCount": 30,
      "recpool": 0,
      "isTop": 0
    },
    {
      "template": 9,
      "mediaId": "6444859495746109442",
      "recreason": 0,
      "createTime": 1550750343,
      "recommendEvent": 0,
      "virtualTime": 1550823978747,
      "videos": [
        {
          "duration": 100.0,
          "hd_id": 0,
          "rate": "0",
          "definitionInfos": [
            {
              "url": "http://v.cdn.sohu.com/93/d3853c6f06f21679ebed5c8959f39c2f/0",
              "size": 4247653
            },
            {
              "url": "http://v.cdn.sohu.com/93/d3853c6f06f21679ebed5c8959f39c2f/1",
              "size": 3937848
            }
          ],
          "type": 0,
          "url": "http://v.cdn.sohu.com/93/d3853c6f06f21679ebed5c8959f39c2f/0",
          "size": 4247653
        }
      ],
      "keyword": "玩具 母婴",
      "score": 0.1184071656403,
      "mediaName": "影视TOP榜",
      "state": 0,
      "isRec": 0,
      "contentType": 3,
      "picNum": 0,
      "articleUrl": "http://c.cdn.sohu.com/article/6504322754987165697",
      "commentNum": 0,
      "filterWords": [
        {
          "name": "屏蔽来源:影视TOP榜",
          "type": "media"
        },
        {
          "name": "不想看:玩具",
          "type": "keyword"
        },
        {
          "name": "不想看:母婴",
          "type": "keyword"
        },
        {
          "name": "不感兴趣",
          "type": "unlike"
        }
      ],
      "pics": [
        {
          "height": 360,
          "width": 640,
          "url": "http://p.cdn.sohu.com/089a1b13/6d5e5bfdbb7c0f7c04ea303773374c60"
        }
      ],
      "title": "汪汪队：半夜有鬼荡秋千，把小砾吓坏了，太吓人了",
      "category": {
        "id": 100,
        "name": "其他"
      },
      "newsId": "6504322754987165697",
      "abs": "",
      "playCount": 142,
      "recpool": 0,
      "isTop": 0
    },
    {
      "template": 9,
      "mediaId": "6450870627296346112",
      "recreason": 0,
      "createTime": 1550630336,
      "recommendEvent": 0,
      "virtualTime": 1550823912081,
      "videos": [
        {
          "duration": 76.0,
          "hd_id": 0,
          "rate": "0",
          "definitionInfos": [
            {
              "url": "http://v.cdn.sohu.com/0/e45b10c12a2fca01f867cd9cdf748532/0",
              "size": 3759102
            }
          ],
          "type": 0,
          "url": "http://v.cdn.sohu.com/0/e45b10c12a2fca01f867cd9cdf748532/0",
          "size": 3759102
        }
      ],
      "keyword": "红烧肉 慈祥 母婴",
      "score": 0.08724858823202669,
      "mediaName": "快乐无极限哈哈哈哈",
      "state": 0,
      "isRec": 0,
      "contentType": 3,
      "picNum": 0,
      "articleUrl": "http://c.cdn.sohu.com/article/6503861037471631361",
      "commentNum": 0,
      "filterWords": [
        {
          "name": "屏蔽来源:快乐无极限哈哈哈哈",
          "type": "media"
        },
        {
          "name": "不想看:红烧肉",
          "type": "keyword"
        },
        {
          "name": "不想看:慈祥",
          "type": "keyword"
        },
        {
          "name": "不想看:母婴",
          "type": "keyword"
        },
        {
          "name": "不感兴趣",
          "type": "unlike"
        }
      ],
      "pics": [
        {
          "height": 486,
          "width": 870,
          "url": "http://p.cdn.sohu.com/cdedd044/5688e60e7f7e1a0dc52b5e961bc859b4"
        }
      ],
      "title": "谁说谎呢！小头爸爸说最爱吃糖醋排骨，老头爷爷却说他爱吃烤鸭",
      "category": {
        "id": 100,
        "name": "其他"
      },
      "newsId": "6503861037471631361",
      "abs": "",
      "playCount": 746,
      "recpool": 0,
      "isTop": 0
    },
    {
      "template": 9,
      "mediaId": "6463053630567088132",
      "recreason": 0,
      "createTime": 1550799804,
      "recommendEvent": 0,
      "virtualTime": 1550823845415,
      "videos": [
        {
          "duration": 61.0,
          "hd_id": 0,
          "rate": "0",
          "definitionInfos": [
            {
              "url": "http://v.cdn.sohu.com/93/e136582dae3b574f5f82915edaec6bd2/0",
              "size": 5690776
            },
            {
              "url": "http://v.cdn.sohu.com/93/e136582dae3b574f5f82915edaec6bd2/1",
              "size": 2819623
            }
          ],
          "type": 0,
          "url": "http://v.cdn.sohu.com/93/e136582dae3b574f5f82915edaec6bd2/0",
          "size": 5690776
        }
      ],
      "keyword": "熊 火影忍者 母婴",
      "score": 0.06525967460321377,
      "mediaName": "育儿圈子在这里",
      "state": 0,
      "isRec": 0,
      "contentType": 3,
      "picNum": 0,
      "articleUrl": "http://c.cdn.sohu.com/article/6504531893914961921",
      "commentNum": 0,
      "filterWords": [
        {
          "name": "屏蔽来源:育儿圈子在这里",
          "type": "media"
        },
        {
          "name": "不想看:熊",
          "type": "keyword"
        },
        {
          "name": "不想看:火影忍者",
          "type": "keyword"
        },
        {
          "name": "不想看:母婴",
          "type": "keyword"
        },
        {
          "name": "不感兴趣",
          "type": "unlike"
        }
      ],
      "pics": [
        {
          "height": 781,
          "width": 1392,
          "url": "http://p.cdn.sohu.com/089a1b13/ad7a909282f938836ac4e371a3075dc8"
        }
      ],
      "title": "熊出没：熊二使出忍术“变蛇术”，成功突破防线，终于出来了",
      "category": {
        "id": 100,
        "name": "其他"
      },
      "newsId": "6504531893914961921",
      "abs": "",
      "playCount": 4,
      "recpool": 0,
      "isTop": 0
    },
    {
      "template": 9,
      "mediaId": "6496603117214236673",
      "recreason": 0,
      "createTime": 1550639689,
      "recommendEvent": 0,
      "virtualTime": 1550823778749,
      "videos": [
        {
          "duration": 192.0,
          "hd_id": 0,
          "rate": "0",
          "definitionInfos": [
            {
              "url": "http://v.cdn.sohu.com/93/31fd9f095441ec70f515d6cbade4ec50/1",
              "size": 18025918
            },
            {
              "url": "http://v.cdn.sohu.com/93/31fd9f095441ec70f515d6cbade4ec50/0",
              "size": 9286857
            }
          ],
          "type": 0,
          "url": "http://v.cdn.sohu.com/93/31fd9f095441ec70f515d6cbade4ec50/1",
          "size": 18025918
        }
      ],
      "keyword": "游戏 母婴",
      "score": 0.059713600511929935,
      "mediaName": "小花搞笑",
      "state": 0,
      "isRec": 0,
      "contentType": 3,
      "picNum": 0,
      "articleUrl": "http://c.cdn.sohu.com/article/6503862903848830976",
      "commentNum": 0,
      "filterWords": [
        {
          "name": "屏蔽来源:小花搞笑",
          "type": "media"
        },
        {
          "name": "不想看:游戏",
          "type": "keyword"
        },
        {
          "name": "不想看:母婴",
          "type": "keyword"
        },
        {
          "name": "不感兴趣",
          "type": "unlike"
        }
      ],
      "pics": [
        {
          "height": 675,
          "width": 1200,
          "url": "http://p.cdn.sohu.com/covers/089a1b13/5492d9d8af8812896dcd472e14e12a7c.jpeg"
        }
      ],
      "title": "汪汪队立大功游戏，玩游戏认颜色，儿童趣味游戏",
      "category": {
        "id": 100,
        "name": "其他"
      },
      "newsId": "6503862903848830976",
      "abs": "",
      "playCount": 35,
      "recpool": 0,
      "isTop": 0
    },
    {
      "template": 9,
      "mediaId": "6468110277530353664",
      "recreason": 0,
      "createTime": 1550657740,
      "recommendEvent": 0,
      "virtualTime": 1550823712083,
      "videos": [
        {
          "duration": 87.0,
          "hd_id": 0,
          "rate": "0",
          "definitionInfos": [
            {
              "url": "http://v.cdn.sohu.com/93/578b2cd8bbf1f5ff3320f5e70954092a/1",
              "size": 7223190
            },
            {
              "url": "http://v.cdn.sohu.com/93/578b2cd8bbf1f5ff3320f5e70954092a/0",
              "size": 5044758
            }
          ],
          "type": 0,
          "url": "http://v.cdn.sohu.com/93/578b2cd8bbf1f5ff3320f5e70954092a/1",
          "size": 7223190
        }
      ],
      "keyword": "超人 蝙蝠侠 母婴",
      "score": 0.054774719927452885,
      "mediaName": "小仙女梦场",
      "state": 0,
      "isRec": 0,
      "contentType": 3,
      "picNum": 0,
      "articleUrl": "http://c.cdn.sohu.com/article/6504022961660364801",
      "commentNum": 0,
      "filterWords": [
        {
          "name": "屏蔽来源:小仙女梦场",
          "type": "media"
        },
        {
          "name": "不想看:超人",
          "type": "keyword"
        },
        {
          "name": "不想看:蝙蝠侠",
          "type": "keyword"
        },
        {
          "name": "不想看:母婴",
          "type": "keyword"
        },
        {
          "name": "不感兴趣",
          "type": "unlike"
        }
      ],
      "pics": [
        {
          "height": 414,
          "width": 750,
          "url": "http://p.cdn.sohu.com/covers/089a1b13/479affc8da5d4a4354397c0d15ad433c.jpeg"
        }
      ],
      "title": "竞球小英雄：超人强使用冰块，弄断了洛基控制队友的丝线！",
      "category": {
        "id": 100,
        "name": "其他"
      },
      "newsId": "6504022961660364801",
      "abs": "",
      "playCount": 11,
      "recpool": 0,
      "isTop": 0
    },
    {
      "template": 9,
      "mediaId": "6483732135592067074",
      "recreason": 0,
      "createTime": 1550484658,
      "recommendEvent": 0,
      "virtualTime": 1550823645417,
      "videos": [
        {
          "duration": 132.0,
          "hd_id": 0,
          "rate": "0",
          "definitionInfos": [
            {
              "url": "http://v.cdn.sohu.com/14/aa0dc40e59aeb1a8eee55b81fa4bd0cc",
              "size": 10515532
            }
          ],
          "type": 0,
          "url": "http://v.cdn.sohu.com/14/aa0dc40e59aeb1a8eee55b81fa4bd0cc",
          "size": 10515532
        }
      ],
      "keyword": "童书绘本 鳄鱼 母婴",
      "score": 0.046152280642695734,
      "mediaName": "娱乐急报小云",
      "state": 0,
      "isRec": 0,
      "contentType": 3,
      "picNum": 0,
      "articleUrl": "http://c.cdn.sohu.com/article/6503850861121243137",
      "commentNum": 0,
      "filterWords": [
        {
          "name": "屏蔽来源:娱乐急报小云",
          "type": "media"
        },
        {
          "name": "不想看:童书绘本",
          "type": "keyword"
        },
        {
          "name": "不想看:鳄鱼",
          "type": "keyword"
        },
        {
          "name": "不想看:母婴",
          "type": "keyword"
        },
        {
          "name": "不感兴趣",
          "type": "unlike"
        }
      ],
      "pics": [
        {
          "height": 712,
          "width": 1280,
          "url": "http://p.cdn.sohu.com/df62730c/thumb/ef8ba7754bd067a0eadd1e31f85f5431.jpeg"
        }
      ],
      "title": "儿童玩具：小鸭子的蛋被蛇偷走，马上呼叫绿巨人帮寻回！",
      "category": {
        "id": 100,
        "name": "其他"
      },
      "newsId": "6503850861121243137",
      "abs": "",
      "playCount": 8,
      "recpool": 0,
      "isTop": 0
    }
  ],
  "channelId": 157,
  "ip": "180.111.35.154",
  "city": "栖霞区",
  "message": "success",
  "totalNum": 10,
  "exts": "chan:o,home:N_T,rank:o,loadId:86706023ee240,ins_Tag:T_D,homeRecall:model,EE:o,INeg:n,video:O_O",
  "reqtype": 0,
  "supplement": 1,
  "errorCode": 0,
  "adcode": "320113",
  "ads": "%EF%BB%BF%7B%0A%20%20%22ads%22%3A%20%5B%0A%20%20%20%20%7B%0A%20%20%20%20%20%20%22itemspace_id%22%3A%20%221000004%22%2C%0A%20%20%20%20%20%20%22position%22%3A%2011%2C%0A%20%20%20%20%20%20%22ad_style%22%3A%201%2C%0A%20%20%20%20%20%20%22advertiser%22%3A%20%22%E6%9C%A8%E5%85%B0%E5%90%88%E9%87%91%22%2C%0A%20%20%20%20%20%20%22dsp_source%22%3A%20%22%22%2C%0A%20%20%20%20%20%20%22form%22%3A%20%22info_bigpictxt%22%2C%0A%20%20%20%20%20%20%22online%22%3A%20%221550764800%22%2C%0A%20%20%20%20%20%20%22offline%22%3A%20%222145801600%22%2C%0A%20%20%20%20%20%20%22title%22%3A%20%22%E5%97%A8%EF%BC%81%E8%80%81%E5%BC%9F%EF%BC%8C%E9%A2%86%E4%BA%86%E7%BA%A2%E5%8C%85%E5%86%8D%E8%B5%B0%7E%22%2C%0A%20%20%20%20%20%20%22body%22%3A%20%22%22%2C%0A%20%20%20%20%20%20%22btn_text%22%3A%20%22%22%2C%0A%20%20%20%20%20%20%22error_code%22%3A%200%2C%0A%20%20%20%20%20%20%22trackings%22%3A%20%7B%0A%20%20%20%20%20%20%20%20%22impression%22%3A%20%7B%0A%20%20%20%20%20%20%20%20%20%20%22sohu_urls%22%3A%20%5B%22https%3A%2F%2Ft.ads.sohu.com%2Fcount%2Fav%3Fimpid%3D0353435e3258ef782_0_0%26appid%3Dsquirrel%26itemspaceid%3D1000004%26viewmonitor%3De%253Dd2o2BlrvgQKTxeySuIFcTaVKdu9jXE0QpQbc%252BMcNJ%252BZGcUfrGeRFrlWXI0RCHo9hPbHEq5%252FdAWVksB4p8kjCwBch7wHrF3rXaktoKQGu4uImdQMECgEeCrEG6YcuujmPr1Q1EHR1UAaGh2xGjYSCbxuYQoGkywzUDsjMysDjwPxtFgP8K4mpLqRv1BY6sikCVE000Ap%252Fei7DeaE9oRVSXwsoM%252F0H1Bzg%252FKl%252FO3q%252Bm7NJF%252BdbDbaM8ymmafj8wqBTjVX9kOoh7EPZLqXSSdFhg8o6GovNunzP7aWSFvHy0qKTBLhrHMcm69FqNxpEkrKgyS6QnLLCOFhqMsd0IYOLoaFQXtlkffPm3V1c9Bpcri8nyivvDAvu6uAK%252BycAqSuwGP9xNyo25qTpgNNdkRGBboZOq%252FD71PidsXlwuPjnGbsWi4uno9KUh%252BD%252FDe35dj2idBMmEHrRJoCatWXVqNYkf%252BdYOdirdLDmi5zKdMCt3wj4lDhNjfikz8SOtcHJ9uynLaYFKlJkGAEPpjodwVOII3skzGxNI290Aw7bK8hn2nWzEXp3YwgG6gdpvSgyRu5Qra0NlXWrqzcDekL5%252FLXB%252BgtAIuZOAm8skF15%252FCp3ZimDTJIUw5%252B5wYEllqGLnEO1WjMFxSViBN0zGq6uHPX452LvSU0B%252BBbyVbUudwbsRNtSB01ITjfQhvmn%252B2iFWWLo4H34fvn4HX9AMtC5kRUdPQ1Q1ij8Vd%252FsDvrzFN2bHa7AeeMHVf1QPocddKm0MMQM%2509tt2%253D1550824245422%2509turn%253D4%2509geoid1%253D1156320100%2509geoid2%253D1156320100%2509source%253Dshjtsybxpsyq%26clickmonitor%3Dc%26mkey%3D0353435e3258ef782_0_0%26deeplink%3D0%26position%3D11%26turn%3D4%26lc%3D0%26rc%3D2%26rr%3D2%26action%3D2%26ip%3D180.111.35.154%26newschn%3D157%26appv%3D3.5.57%26sdkv%3D1.5.0%26appchn%3D1%26os%3DAndroid%26osv%3D7.0%26nets%3Dwifi%26carrier%3Dunknown%26pn%3DSLA-AL00%26scs%3D72001280%26mac%3D54%3AB1%3A21%3AB8%3A76%3A2E%26imei%3D866534039422549%26imsi%3Dnull%26androidid%3D866534039422549%26did%3D2a1f3afe-22bd-3c4d-b11f-d4218d01595b%22%5D%0A%20%20%20%20%20%20%20%20%7D%2C%0A%20%20%20%20%20%20%20%20%22load%22%3A%20%7B%0A%20%20%20%20%20%20%20%20%20%20%22sohu_urls%22%3A%20%5B%22https%3A%2F%2Ft.ads.sohu.com%2Fcount%2Fv%3Fimpid%3D0353435e3258ef782_0_0%26appid%3Dsquirrel%26itemspaceid%3D1000004%26viewmonitor%3De%253Dd2o2BlrvgQKTxeySuIFcTaVKdu9jXE0QpQbc%252BMcNJ%252BZGcUfrGeRFrlWXI0RCHo9hPbHEq5%252FdAWVksB4p8kjCwBch7wHrF3rXaktoKQGu4uImdQMECgEeCrEG6YcuujmPr1Q1EHR1UAaGh2xGjYSCbxuYQoGkywzUDsjMysDjwPxtFgP8K4mpLqRv1BY6sikCVE000Ap%252Fei7DeaE9oRVSXwsoM%252F0H1Bzg%252FKl%252FO3q%252Bm7NJF%252BdbDbaM8ymmafj8wqBTjVX9kOoh7EPZLqXSSdFhg8o6GovNunzP7aWSFvHy0qKTBLhrHMcm69FqNxpEkrKgyS6QnLLCOFhqMsd0IYOLoaFQXtlkffPm3V1c9Bpcri8nyivvDAvu6uAK%252BycAqSuwGP9xNyo25qTpgNNdkRGBboZOq%252FD71PidsXlwuPjnGbsWi4uno9KUh%252BD%252FDe35dj2idBMmEHrRJoCatWXVqNYkf%252BdYOdirdLDmi5zKdMCt3wj4lDhNjfikz8SOtcHJ9uynLaYFKlJkGAEPpjodwVOII3skzGxNI290Aw7bK8hn2nWzEXp3YwgG6gdpvSgyRu5Qra0NlXWrqzcDekL5%252FLXB%252BgtAIuZOAm8skF15%252FCp3ZimDTJIUw5%252B5wYEllqGLnEO1WjMFxSViBN0zGq6uHPX452LvSU0B%252BBbyVbUudwbsRNtSB01ITjfQhvmn%252B2iFWWLo4H34fvn4HX9AMtC5kRUdPQ1Q1ij8Vd%252FsDvrzFN2bHa7AeeMHVf1QPocddKm0MMQM%2509tt2%253D1550824245422%2509turn%253D4%2509geoid1%253D1156320100%2509geoid2%253D1156320100%2509source%253Dshjtsybxpsyq%26clickmonitor%3Dc%26mkey%3D0353435e3258ef782_0_0%26deeplink%3D0%26position%3D11%26turn%3D4%26lc%3D0%26rc%3D2%26rr%3D2%26action%3D2%26ip%3D180.111.35.154%26newschn%3D157%26appv%3D3.5.57%26sdkv%3D1.5.0%26appchn%3D1%26os%3DAndroid%26osv%3D7.0%26nets%3Dwifi%26carrier%3Dunknown%26pn%3DSLA-AL00%26scs%3D72001280%26mac%3D54%3AB1%3A21%3AB8%3A76%3A2E%26imei%3D866534039422549%26imsi%3Dnull%26androidid%3D866534039422549%26did%3D2a1f3afe-22bd-3c4d-b11f-d4218d01595b%22%5D%2C%0A%20%20%20%20%20%20%20%20%20%20%22miaozhen_sdk_urls%22%3A%20%5B%5D%2C%0A%20%20%20%20%20%20%20%20%20%20%22admaster_sdk_urls%22%3A%20%5B%5D%2C%0A%20%20%20%20%20%20%20%20%20%20%22other_urls%22%3A%20%5B%5D%0A%20%20%20%20%20%20%20%20%7D%2C%0A%20%20%20%20%20%20%20%20%22click%22%3A%20%7B%0A%20%20%20%20%20%20%20%20%20%20%22sohu_urls%22%3A%20%5B%22https%3A%2F%2Ft.ads.sohu.com%2Fcount%2Fc%3Fclicktype%3D0%26impid%3D0353435e3258ef782_0_0%26appid%3Dsquirrel%26itemspaceid%3D1000004%26viewmonitor%3De%253Dd2o2BlrvgQKTxeySuIFcTaVKdu9jXE0QpQbc%252BMcNJ%252BZGcUfrGeRFrlWXI0RCHo9hPbHEq5%252FdAWVksB4p8kjCwBch7wHrF3rXaktoKQGu4uImdQMECgEeCrEG6YcuujmPr1Q1EHR1UAaGh2xGjYSCbxuYQoGkywzUDsjMysDjwPxtFgP8K4mpLqRv1BY6sikCVE000Ap%252Fei7DeaE9oRVSXwsoM%252F0H1Bzg%252FKl%252FO3q%252Bm7NJF%252BdbDbaM8ymmafj8wqBTjVX9kOoh7EPZLqXSSdFhg8o6GovNunzP7aWSFvHy0qKTBLhrHMcm69FqNxpEkrKgyS6QnLLCOFhqMsd0IYOLoaFQXtlkffPm3V1c9Bpcri8nyivvDAvu6uAK%252BycAqSuwGP9xNyo25qTpgNNdkRGBboZOq%252FD71PidsXlwuPjnGbsWi4uno9KUh%252BD%252FDe35dj2idBMmEHrRJoCatWXVqNYkf%252BdYOdirdLDmi5zKdMCt3wj4lDhNjfikz8SOtcHJ9uynLaYFKlJkGAEPpjodwVOII3skzGxNI290Aw7bK8hn2nWzEXp3YwgG6gdpvSgyRu5Qra0NlXWrqzcDekL5%252FLXB%252BgtAIuZOAm8skF15%252FCp3ZimDTJIUw5%252B5wYEllqGLnEO1WjMFxSViBN0zGq6uHPX452LvSU0B%252BBbyVbUudwbsRNtSB01ITjfQhvmn%252B2iFWWLo4H34fvn4HX9AMtC5kRUdPQ1Q1ij8Vd%252FsDvrzFN2bHa7AeeMHVf1QPocddKm0MMQM%2509tt2%253D1550824245422%2509turn%253D4%2509geoid1%253D1156320100%2509geoid2%253D1156320100%2509source%253Dshjtsybxpsyq%26clickmonitor%3Dc%26mkey%3D0353435e3258ef782_0_0%26deeplink%3D0%26position%3D11%26turn%3D4%26lc%3D0%26rc%3D2%26rr%3D2%26action%3D2%26ip%3D180.111.35.154%26newschn%3D157%26appv%3D3.5.57%26sdkv%3D1.5.0%26appchn%3D1%26os%3DAndroid%26osv%3D7.0%26nets%3Dwifi%26carrier%3Dunknown%26pn%3DSLA-AL00%26scs%3D72001280%26mac%3D54%3AB1%3A21%3AB8%3A76%3A2E%26imei%3D866534039422549%26imsi%3Dnull%26androidid%3D866534039422549%26did%3D2a1f3afe-22bd-3c4d-b11f-d4218d01595b%22%5D%2C%0A%20%20%20%20%20%20%20%20%20%20%22miaozhen_sdk_urls%22%3A%20%5B%5D%2C%0A%20%20%20%20%20%20%20%20%20%20%22admaster_sdk_urls%22%3A%20%5B%5D%2C%0A%20%20%20%20%20%20%20%20%20%20%22other_urls%22%3A%20%5B%5D%0A%20%20%20%20%20%20%20%20%7D%2C%0A%20%20%20%20%20%20%20%20%22video_start%22%3A%20%7B%0A%20%20%20%20%20%20%20%20%20%20%22sohu_urls%22%3A%20%5B%5D%2C%0A%20%20%20%20%20%20%20%20%20%20%22miaozhen_sdk_urls%22%3A%20%5B%5D%2C%0A%20%20%20%20%20%20%20%20%20%20%22admaster_sdk_urls%22%3A%20%5B%5D%2C%0A%20%20%20%20%20%20%20%20%20%20%22other_urls%22%3A%20%5B%5D%0A%20%20%20%20%20%20%20%20%7D%2C%0A%20%20%20%20%20%20%20%20%22video_complete%22%3A%20%7B%0A%20%20%20%20%20%20%20%20%20%20%22sohu_urls%22%3A%20%5B%5D%2C%0A%20%20%20%20%20%20%20%20%20%20%22miaozhen_sdk_urls%22%3A%20%5B%5D%2C%0A%20%20%20%20%20%20%20%20%20%20%22admaster_sdk_urls%22%3A%20%5B%5D%2C%0A%20%20%20%20%20%20%20%20%20%20%22other_urls%22%3A%20%5B%5D%0A%20%20%20%20%20%20%20%20%7D%2C%0A%20%20%20%20%20%20%20%20%22video_pause%22%3A%20%7B%0A%20%20%20%20%20%20%20%20%20%20%22sohu_urls%22%3A%20%5B%5D%2C%0A%20%20%20%20%20%20%20%20%20%20%22miaozhen_sdk_urls%22%3A%20%5B%5D%2C%0A%20%20%20%20%20%20%20%20%20%20%22admaster_sdk_urls%22%3A%20%5B%5D%2C%0A%20%20%20%20%20%20%20%20%20%20%22other_urls%22%3A%20%5B%5D%0A%20%20%20%20%20%20%20%20%7D%2C%0A%20%20%20%20%20%20%20%20%22not_interest%22%3A%20%7B%0A%20%20%20%20%20%20%20%20%20%20%22sohu_urls%22%3A%20%5B%22https%3A%2F%2Ft.ads.sohu.com%2Fcount%2Fneg%3Fimpid%3D0353435e3258ef782_0_0%26appid%3Dsquirrel%26itemspaceid%3D1000004%26viewmonitor%3De%253Dd2o2BlrvgQKTxeySuIFcTaVKdu9jXE0QpQbc%252BMcNJ%252BZGcUfrGeRFrlWXI0RCHo9hPbHEq5%252FdAWVksB4p8kjCwBch7wHrF3rXaktoKQGu4uImdQMECgEeCrEG6YcuujmPr1Q1EHR1UAaGh2xGjYSCbxuYQoGkywzUDsjMysDjwPxtFgP8K4mpLqRv1BY6sikCVE000Ap%252Fei7DeaE9oRVSXwsoM%252F0H1Bzg%252FKl%252FO3q%252Bm7NJF%252BdbDbaM8ymmafj8wqBTjVX9kOoh7EPZLqXSSdFhg8o6GovNunzP7aWSFvHy0qKTBLhrHMcm69FqNxpEkrKgyS6QnLLCOFhqMsd0IYOLoaFQXtlkffPm3V1c9Bpcri8nyivvDAvu6uAK%252BycAqSuwGP9xNyo25qTpgNNdkRGBboZOq%252FD71PidsXlwuPjnGbsWi4uno9KUh%252BD%252FDe35dj2idBMmEHrRJoCatWXVqNYkf%252BdYOdirdLDmi5zKdMCt3wj4lDhNjfikz8SOtcHJ9uynLaYFKlJkGAEPpjodwVOII3skzGxNI290Aw7bK8hn2nWzEXp3YwgG6gdpvSgyRu5Qra0NlXWrqzcDekL5%252FLXB%252BgtAIuZOAm8skF15%252FCp3ZimDTJIUw5%252B5wYEllqGLnEO1WjMFxSViBN0zGq6uHPX452LvSU0B%252BBbyVbUudwbsRNtSB01ITjfQhvmn%252B2iFWWLo4H34fvn4HX9AMtC5kRUdPQ1Q1ij8Vd%252FsDvrzFN2bHa7AeeMHVf1QPocddKm0MMQM%2509tt2%253D1550824245422%2509turn%253D4%2509geoid1%253D1156320100%2509geoid2%253D1156320100%2509source%253Dshjtsybxpsyq%26clickmonitor%3Dc%26mkey%3D0353435e3258ef782_0_0%26deeplink%3D0%26position%3D11%26turn%3D4%26lc%3D0%26rc%3D2%26rr%3D2%26action%3D2%26ip%3D180.111.35.154%26newschn%3D157%26appv%3D3.5.57%26sdkv%3D1.5.0%26appchn%3D1%26os%3DAndroid%26osv%3D7.0%26nets%3Dwifi%26carrier%3Dunknown%26pn%3DSLA-AL00%26scs%3D72001280%26mac%3D54%3AB1%3A21%3AB8%3A76%3A2E%26imei%3D866534039422549%26imsi%3Dnull%26androidid%3D866534039422549%26did%3D2a1f3afe-22bd-3c4d-b11f-d4218d01595b%22%5D%2C%0A%20%20%20%20%20%20%20%20%20%20%22miaozhen_sdk_urls%22%3A%20%5B%5D%2C%0A%20%20%20%20%20%20%20%20%20%20%22admaster_sdk_urls%22%3A%20%5B%5D%2C%0A%20%20%20%20%20%20%20%20%20%20%22other_urls%22%3A%20%5B%5D%0A%20%20%20%20%20%20%20%20%7D%2C%0A%20%20%20%20%20%20%20%20%22discard%22%3A%20%7B%0A%20%20%20%20%20%20%20%20%20%20%22sohu_urls%22%3A%20%5B%22https%3A%2F%2Ft.ads.sohu.com%2Fcount%2Funuse%3Fimpid%3D0353435e3258ef782_0_0%26appid%3Dsquirrel%26itemspaceid%3D1000004%26viewmonitor%3De%253Dd2o2BlrvgQKTxeySuIFcTaVKdu9jXE0QpQbc%252BMcNJ%252BZGcUfrGeRFrlWXI0RCHo9hPbHEq5%252FdAWVksB4p8kjCwBch7wHrF3rXaktoKQGu4uImdQMECgEeCrEG6YcuujmPr1Q1EHR1UAaGh2xGjYSCbxuYQoGkywzUDsjMysDjwPxtFgP8K4mpLqRv1BY6sikCVE000Ap%252Fei7DeaE9oRVSXwsoM%252F0H1Bzg%252FKl%252FO3q%252Bm7NJF%252BdbDbaM8ymmafj8wqBTjVX9kOoh7EPZLqXSSdFhg8o6GovNunzP7aWSFvHy0qKTBLhrHMcm69FqNxpEkrKgyS6QnLLCOFhqMsd0IYOLoaFQXtlkffPm3V1c9Bpcri8nyivvDAvu6uAK%252BycAqSuwGP9xNyo25qTpgNNdkRGBboZOq%252FD71PidsXlwuPjnGbsWi4uno9KUh%252BD%252FDe35dj2idBMmEHrRJoCatWXVqNYkf%252BdYOdirdLDmi5zKdMCt3wj4lDhNjfikz8SOtcHJ9uynLaYFKlJkGAEPpjodwVOII3skzGxNI290Aw7bK8hn2nWzEXp3YwgG6gdpvSgyRu5Qra0NlXWrqzcDekL5%252FLXB%252BgtAIuZOAm8skF15%252FCp3ZimDTJIUw5%252B5wYEllqGLnEO1WjMFxSViBN0zGq6uHPX452LvSU0B%252BBbyVbUudwbsRNtSB01ITjfQhvmn%252B2iFWWLo4H34fvn4HX9AMtC5kRUdPQ1Q1ij8Vd%252FsDvrzFN2bHa7AeeMHVf1QPocddKm0MMQM%2509tt2%253D1550824245422%2509turn%253D4%2509geoid1%253D1156320100%2509geoid2%253D1156320100%2509source%253Dshjtsybxpsyq%26clickmonitor%3Dc%26mkey%3D0353435e3258ef782_0_0%26deeplink%3D0%26position%3D11%26turn%3D4%26lc%3D0%26rc%3D2%26rr%3D2%26action%3D2%26ip%3D180.111.35.154%26newschn%3D157%26appv%3D3.5.57%26sdkv%3D1.5.0%26appchn%3D1%26os%3DAndroid%26osv%3D7.0%26nets%3Dwifi%26carrier%3Dunknown%26pn%3DSLA-AL00%26scs%3D72001280%26mac%3D54%3AB1%3A21%3AB8%3A76%3A2E%26imei%3D866534039422549%26imsi%3Dnull%26androidid%3D866534039422549%26did%3D2a1f3afe-22bd-3c4d-b11f-d4218d01595b%22%5D%2C%0A%20%20%20%20%20%20%20%20%20%20%22miaozhen_sdk_urls%22%3A%20%5B%5D%2C%0A%20%20%20%20%20%20%20%20%20%20%22admaster_sdk_urls%22%3A%20%5B%5D%2C%0A%20%20%20%20%20%20%20%20%20%20%22other_urls%22%3A%20%5B%5D%0A%20%20%20%20%20%20%20%20%7D%2C%0A%20%20%20%20%20%20%20%20%22timeout%22%3A%20%7B%0A%20%20%20%20%20%20%20%20%20%20%22sohu_urls%22%3A%20%5B%22https%3A%2F%2Ft.ads.sohu.com%2Fcount%2Ftoav%3Fimpid%3D0353435e3258ef782_0_0%26appid%3Dsquirrel%26itemspaceid%3D1000004%26viewmonitor%3De%253Dd2o2BlrvgQKTxeySuIFcTaVKdu9jXE0QpQbc%252BMcNJ%252BZGcUfrGeRFrlWXI0RCHo9hPbHEq5%252FdAWVksB4p8kjCwBch7wHrF3rXaktoKQGu4uImdQMECgEeCrEG6YcuujmPr1Q1EHR1UAaGh2xGjYSCbxuYQoGkywzUDsjMysDjwPxtFgP8K4mpLqRv1BY6sikCVE000Ap%252Fei7DeaE9oRVSXwsoM%252F0H1Bzg%252FKl%252FO3q%252Bm7NJF%252BdbDbaM8ymmafj8wqBTjVX9kOoh7EPZLqXSSdFhg8o6GovNunzP7aWSFvHy0qKTBLhrHMcm69FqNxpEkrKgyS6QnLLCOFhqMsd0IYOLoaFQXtlkffPm3V1c9Bpcri8nyivvDAvu6uAK%252BycAqSuwGP9xNyo25qTpgNNdkRGBboZOq%252FD71PidsXlwuPjnGbsWi4uno9KUh%252BD%252FDe35dj2idBMmEHrRJoCatWXVqNYkf%252BdYOdirdLDmi5zKdMCt3wj4lDhNjfikz8SOtcHJ9uynLaYFKlJkGAEPpjodwVOII3skzGxNI290Aw7bK8hn2nWzEXp3YwgG6gdpvSgyRu5Qra0NlXWrqzcDekL5%252FLXB%252BgtAIuZOAm8skF15%252FCp3ZimDTJIUw5%252B5wYEllqGLnEO1WjMFxSViBN0zGq6uHPX452LvSU0B%252BBbyVbUudwbsRNtSB01ITjfQhvmn%252B2iFWWLo4H34fvn4HX9AMtC5kRUdPQ1Q1ij8Vd%252FsDvrzFN2bHa7AeeMHVf1QPocddKm0MMQM%2509tt2%253D1550824245422%2509turn%253D4%2509geoid1%253D1156320100%2509geoid2%253D1156320100%2509source%253Dshjtsybxpsyq%26clickmonitor%3Dc%26mkey%3D0353435e3258ef782_0_0%26deeplink%3D0%26position%3D11%26turn%3D4%26lc%3D0%26rc%3D2%26rr%3D2%26action%3D2%26ip%3D180.111.35.154%26newschn%3D157%26appv%3D3.5.57%26sdkv%3D1.5.0%26appchn%3D1%26os%3DAndroid%26osv%3D7.0%26nets%3Dwifi%26carrier%3Dunknown%26pn%3DSLA-AL00%26scs%3D72001280%26mac%3D54%3AB1%3A21%3AB8%3A76%3A2E%26imei%3D866534039422549%26imsi%3Dnull%26androidid%3D866534039422549%26did%3D2a1f3afe-22bd-3c4d-b11f-d4218d01595b%22%5D%0A%20%20%20%20%20%20%20%20%7D%0A%20%20%20%20%20%20%7D%2C%0A%20%20%20%20%20%20%22click_action%22%3A%20%7B%0A%20%20%20%20%20%20%20%20%22type%22%3A%201%2C%0A%20%20%20%20%20%20%20%20%22url%22%3A%20%22https%3A%2F%2Fapi.nicetui.cn%2Fniceapi%2Faddpostion%2F597E6C4CA1D745D1%22%2C%0A%20%20%20%20%20%20%20%20%22deeplink%22%3A%20%220%22%0A%20%20%20%20%20%20%7D%2C%0A%20%20%20%20%20%20%22images%22%3A%20%5B%0A%20%20%20%20%20%20%20%20%7B%0A%20%20%20%20%20%20%20%20%20%20%22name%22%3A%20%22picture%22%2C%0A%20%20%20%20%20%20%20%20%20%20%22url%22%3A%20%22https%3A%2F%2F643108e7617ef.cdn.sohucs.com%2Fe03d0354be2149e4abbdea5721ad2513.jpg%22%2C%0A%20%20%20%20%20%20%20%20%20%20%22width%22%3A%20%22644%22%2C%0A%20%20%20%20%20%20%20%20%20%20%22height%22%3A%20%22322%22%0A%20%20%20%20%20%20%20%20%7D%0A%20%20%20%20%20%20%5D%2C%0A%20%20%20%20%20%20%22icon%22%3A%20%7B%0A%20%20%20%20%20%20%7D%2C%0A%20%20%20%20%20%20%22video%22%3A%20%7B%0A%20%20%20%20%20%20%7D%2C%0A%20%20%20%20%20%20%22file%22%3A%20%22%22%2C%0A%20%20%20%20%20%20%22ext%22%3A%20%7B%0A%20%20%20%20%20%20%20%20%22vrpttype%22%3A%20%22%22%2C%0A%20%20%20%20%20%20%20%20%22action_call%22%3A%20%7B%0A%20%20%20%20%20%20%20%20%20%20%22type%22%3A%200%2C%0A%20%20%20%20%20%20%20%20%20%20%22url%22%3A%20%22%22%2C%0A%20%20%20%20%20%20%20%20%20%20%22click%22%3A%20%7B%0A%20%20%20%20%20%20%20%20%20%20%20%20%22sohu_urls%22%3A%20%5B%5D%2C%0A%20%20%20%20%20%20%20%20%20%20%20%20%22miaozhen_sdk_urls%22%3A%20%5B%5D%2C%0A%20%20%20%20%20%20%20%20%20%20%20%20%22admaster_sdk_urls%22%3A%20%5B%5D%2C%0A%20%20%20%20%20%20%20%20%20%20%20%20%22other_urls%22%3A%20%5B%5D%0A%20%20%20%20%20%20%20%20%20%20%7D%0A%20%20%20%20%20%20%20%20%7D%2C%0A%20%20%20%20%20%20%20%20%22flag_sensitive%22%3A%220%22%0A%20%20%20%20%20%20%7D%0A%20%20%20%20%7D%2C%0A%20%20%20%20%7B%0A%20%20%20%20%20%20%22itemspace_id%22%3A%20%221000004%22%2C%0A%20%20%20%20%20%20%22position%22%3A%204%2C%0A%20%20%20%20%20%20%22ad_style%22%3A%201%2C%0A%20%20%20%20%20%20%22advertiser%22%3A%20%22%E5%85%BC%E8%81%8C%E5%BA%93%22%2C%0A%20%20%20%20%20%20%22dsp_source%22%3A%20%22%22%2C%0A%20%20%20%20%20%20%22form%22%3A%20%22info_bigpictxt%22%2C%0A%20%20%20%20%20%20%22online%22%3A%20%221548691200%22%2C%0A%20%20%20%20%20%20%22offline%22%3A%20%222145801600%22%2C%0A%20%20%20%20%20%20%22title%22%3A%20%22%E5%9C%A8%E5%AE%B6%E2%89%A0%E5%A4%B1%E4%B8%9A%EF%BC%8C%E5%BE%AE%E4%BF%A1%E5%8A%A8%E5%8A%A8%E6%89%8B%E6%8C%87%E4%B9%9F%E8%83%BD%E6%94%92%E9%92%B1%22%2C%0A%20%20%20%20%20%20%22body%22%3A%20%22%22%2C%0A%20%20%20%20%20%20%22btn_text%22%3A%20%22%22%2C%0A%20%20%20%20%20%20%22error_code%22%3A%200%2C%0A%20%20%20%20%20%20%22trackings%22%3A%20%7B%0A%20%20%20%20%20%20%20%20%22impression%22%3A%20%7B%0A%20%20%20%20%20%20%20%20%20%20%22sohu_urls%22%3A%20%5B%22https%3A%2F%2Ft.ads.sohu.com%2Fcount%2Fav%3Fimpid%3D0353435e3258ef782_0_1%26appid%3Dsquirrel%26itemspaceid%3D1000004%26viewmonitor%3De%253DP0V5jA997wz9DR6lWun16bPq6LUb42HGa9h9erROvydTo5q7cVt0Nb8zA7Ga0BIAeA9k%252FfQqCxvmD28ggECgc%252FiqzJ9itaUNOAOT2ZqSGLHpTqWCaiJ4NJDo279RPtK27JSR8SMVj%252BCmec6yeAMo2zRtNZItBgucs5BCY3yVnlDxoZR23wdAPMYd%252BXvDiCdIJ5fce9zYupiFRsBPF09oYHDWvAI87C106sNrjp1ICB7ja0iQJJy8TrMjNiVrZsBJ%252F7O5368KQMtOc3eX5D7UUtSeSY6pTI%252FHm%252B8SwXumEOk6ZtrbEikAXF1i2wsCSu3ud4RBfKwMmIBSGyXJ3vKqwUVX1UiTbRSfOmW3vmdiMRhY%252BeSeQ%252FkKKfl4aHvE%252FtQ9Uw1WIXTkwOsss%252Bi3lIqe4NKetWBegCWGp6oQKSslzg4QpMy2h98TVQsfWRoHKa30K8BiUd3I1DoJBVT93aX7FNxgtxZGTmRqsDpTT92n8DAfYmxU6ZnhH85sh8Xlc2v%252FDaV%252B5vMJMOsTJZ%252BgM0rqbwTTYXIWiDXJz8uRznkr64eQ8oqmxQOl%252FC1djqck6nJOMNmMni3whj8fonKii%252ByLuS1%252FVW6yIJ1fSvh87mn36gYqod4sGGY3t3IF9hhNveYXBkvMz9L5ZvHf2%252FZH%252FOqWynu6GvINoR%252FljJiz48QQ1zx0XKkF3TFAjfpHCrDiN0Dl2ujXS%252FW5597QDOIAI0xdAsq2BKciQJWcZ8ScKPTtWKIr6fYl9KzzyKKVLRg92Qpt9BaO0dmyUBgxzPaXtDalvg%253D%253D%2509tt2%253D1550824245422%2509turn%253D4%2509geoid1%253D1156320100%2509geoid2%253D1156320100%2509source%253Dshjtsybxpsyq%26clickmonitor%3Dc%26mkey%3D0353435e3258ef782_0_1%26deeplink%3D1%26position%3D4%26turn%3D4%26lc%3D0%26rc%3D2%26rr%3D2%26action%3D2%26ip%3D180.111.35.154%26newschn%3D157%26appv%3D3.5.57%26sdkv%3D1.5.0%26appchn%3D1%26os%3DAndroid%26osv%3D7.0%26nets%3Dwifi%26carrier%3Dunknown%26pn%3DSLA-AL00%26scs%3D72001280%26mac%3D54%3AB1%3A21%3AB8%3A76%3A2E%26imei%3D866534039422549%26imsi%3Dnull%26androidid%3D866534039422549%26did%3D2a1f3afe-22bd-3c4d-b11f-d4218d01595b%22%5D%0A%20%20%20%20%20%20%20%20%7D%2C%0A%20%20%20%20%20%20%20%20%22load%22%3A%20%7B%0A%20%20%20%20%20%20%20%20%20%20%22sohu_urls%22%3A%20%5B%22https%3A%2F%2Ft.ads.sohu.com%2Fcount%2Fv%3Fimpid%3D0353435e3258ef782_0_1%26appid%3Dsquirrel%26itemspaceid%3D1000004%26viewmonitor%3De%253DP0V5jA997wz9DR6lWun16bPq6LUb42HGa9h9erROvydTo5q7cVt0Nb8zA7Ga0BIAeA9k%252FfQqCxvmD28ggECgc%252FiqzJ9itaUNOAOT2ZqSGLHpTqWCaiJ4NJDo279RPtK27JSR8SMVj%252BCmec6yeAMo2zRtNZItBgucs5BCY3yVnlDxoZR23wdAPMYd%252BXvDiCdIJ5fce9zYupiFRsBPF09oYHDWvAI87C106sNrjp1ICB7ja0iQJJy8TrMjNiVrZsBJ%252F7O5368KQMtOc3eX5D7UUtSeSY6pTI%252FHm%252B8SwXumEOk6ZtrbEikAXF1i2wsCSu3ud4RBfKwMmIBSGyXJ3vKqwUVX1UiTbRSfOmW3vmdiMRhY%252BeSeQ%252FkKKfl4aHvE%252FtQ9Uw1WIXTkwOsss%252Bi3lIqe4NKetWBegCWGp6oQKSslzg4QpMy2h98TVQsfWRoHKa30K8BiUd3I1DoJBVT93aX7FNxgtxZGTmRqsDpTT92n8DAfYmxU6ZnhH85sh8Xlc2v%252FDaV%252B5vMJMOsTJZ%252BgM0rqbwTTYXIWiDXJz8uRznkr64eQ8oqmxQOl%252FC1djqck6nJOMNmMni3whj8fonKii%252ByLuS1%252FVW6yIJ1fSvh87mn36gYqod4sGGY3t3IF9hhNveYXBkvMz9L5ZvHf2%252FZH%252FOqWynu6GvINoR%252FljJiz48QQ1zx0XKkF3TFAjfpHCrDiN0Dl2ujXS%252FW5597QDOIAI0xdAsq2BKciQJWcZ8ScKPTtWKIr6fYl9KzzyKKVLRg92Qpt9BaO0dmyUBgxzPaXtDalvg%253D%253D%2509tt2%253D1550824245422%2509turn%253D4%2509geoid1%253D1156320100%2509geoid2%253D1156320100%2509source%253Dshjtsybxpsyq%26clickmonitor%3Dc%26mkey%3D0353435e3258ef782_0_1%26deeplink%3D1%26position%3D4%26turn%3D4%26lc%3D0%26rc%3D2%26rr%3D2%26action%3D2%26ip%3D180.111.35.154%26newschn%3D157%26appv%3D3.5.57%26sdkv%3D1.5.0%26appchn%3D1%26os%3DAndroid%26osv%3D7.0%26nets%3Dwifi%26carrier%3Dunknown%26pn%3DSLA-AL00%26scs%3D72001280%26mac%3D54%3AB1%3A21%3AB8%3A76%3A2E%26imei%3D866534039422549%26imsi%3Dnull%26androidid%3D866534039422549%26did%3D2a1f3afe-22bd-3c4d-b11f-d4218d01595b%22%5D%2C%0A%20%20%20%20%20%20%20%20%20%20%22miaozhen_sdk_urls%22%3A%20%5B%5D%2C%0A%20%20%20%20%20%20%20%20%20%20%22admaster_sdk_urls%22%3A%20%5B%5D%2C%0A%20%20%20%20%20%20%20%20%20%20%22other_urls%22%3A%20%5B%5D%0A%20%20%20%20%20%20%20%20%7D%2C%0A%20%20%20%20%20%20%20%20%22click%22%3A%20%7B%0A%20%20%20%20%20%20%20%20%20%20%22sohu_urls%22%3A%20%5B%22https%3A%2F%2Ft.ads.sohu.com%2Fcount%2Fc%3Fclicktype%3D0%26impid%3D0353435e3258ef782_0_1%26appid%3Dsquirrel%26itemspaceid%3D1000004%26viewmonitor%3De%253DP0V5jA997wz9DR6lWun16bPq6LUb42HGa9h9erROvydTo5q7cVt0Nb8zA7Ga0BIAeA9k%252FfQqCxvmD28ggECgc%252FiqzJ9itaUNOAOT2ZqSGLHpTqWCaiJ4NJDo279RPtK27JSR8SMVj%252BCmec6yeAMo2zRtNZItBgucs5BCY3yVnlDxoZR23wdAPMYd%252BXvDiCdIJ5fce9zYupiFRsBPF09oYHDWvAI87C106sNrjp1ICB7ja0iQJJy8TrMjNiVrZsBJ%252F7O5368KQMtOc3eX5D7UUtSeSY6pTI%252FHm%252B8SwXumEOk6ZtrbEikAXF1i2wsCSu3ud4RBfKwMmIBSGyXJ3vKqwUVX1UiTbRSfOmW3vmdiMRhY%252BeSeQ%252FkKKfl4aHvE%252FtQ9Uw1WIXTkwOsss%252Bi3lIqe4NKetWBegCWGp6oQKSslzg4QpMy2h98TVQsfWRoHKa30K8BiUd3I1DoJBVT93aX7FNxgtxZGTmRqsDpTT92n8DAfYmxU6ZnhH85sh8Xlc2v%252FDaV%252B5vMJMOsTJZ%252BgM0rqbwTTYXIWiDXJz8uRznkr64eQ8oqmxQOl%252FC1djqck6nJOMNmMni3whj8fonKii%252ByLuS1%252FVW6yIJ1fSvh87mn36gYqod4sGGY3t3IF9hhNveYXBkvMz9L5ZvHf2%252FZH%252FOqWynu6GvINoR%252FljJiz48QQ1zx0XKkF3TFAjfpHCrDiN0Dl2ujXS%252FW5597QDOIAI0xdAsq2BKciQJWcZ8ScKPTtWKIr6fYl9KzzyKKVLRg92Qpt9BaO0dmyUBgxzPaXtDalvg%253D%253D%2509tt2%253D1550824245422%2509turn%253D4%2509geoid1%253D1156320100%2509geoid2%253D1156320100%2509source%253Dshjtsybxpsyq%26clickmonitor%3Dc%26mkey%3D0353435e3258ef782_0_1%26deeplink%3D1%26position%3D4%26turn%3D4%26lc%3D0%26rc%3D2%26rr%3D2%26action%3D2%26ip%3D180.111.35.154%26newschn%3D157%26appv%3D3.5.57%26sdkv%3D1.5.0%26appchn%3D1%26os%3DAndroid%26osv%3D7.0%26nets%3Dwifi%26carrier%3Dunknown%26pn%3DSLA-AL00%26scs%3D72001280%26mac%3D54%3AB1%3A21%3AB8%3A76%3A2E%26imei%3D866534039422549%26imsi%3Dnull%26androidid%3D866534039422549%26did%3D2a1f3afe-22bd-3c4d-b11f-d4218d01595b%22%5D%2C%0A%20%20%20%20%20%20%20%20%20%20%22miaozhen_sdk_urls%22%3A%20%5B%5D%2C%0A%20%20%20%20%20%20%20%20%20%20%22admaster_sdk_urls%22%3A%20%5B%5D%2C%0A%20%20%20%20%20%20%20%20%20%20%22other_urls%22%3A%20%5B%5D%0A%20%20%20%20%20%20%20%20%7D%2C%0A%20%20%20%20%20%20%20%20%22video_start%22%3A%20%7B%0A%20%20%20%20%20%20%20%20%20%20%22sohu_urls%22%3A%20%5B%5D%2C%0A%20%20%20%20%20%20%20%20%20%20%22miaozhen_sdk_urls%22%3A%20%5B%5D%2C%0A%20%20%20%20%20%20%20%20%20%20%22admaster_sdk_urls%22%3A%20%5B%5D%2C%0A%20%20%20%20%20%20%20%20%20%20%22other_urls%22%3A%20%5B%5D%0A%20%20%20%20%20%20%20%20%7D%2C%0A%20%20%20%20%20%20%20%20%22video_complete%22%3A%20%7B%0A%20%20%20%20%20%20%20%20%20%20%22sohu_urls%22%3A%20%5B%5D%2C%0A%20%20%20%20%20%20%20%20%20%20%22miaozhen_sdk_urls%22%3A%20%5B%5D%2C%0A%20%20%20%20%20%20%20%20%20%20%22admaster_sdk_urls%22%3A%20%5B%5D%2C%0A%20%20%20%20%20%20%20%20%20%20%22other_urls%22%3A%20%5B%5D%0A%20%20%20%20%20%20%20%20%7D%2C%0A%20%20%20%20%20%20%20%20%22video_pause%22%3A%20%7B%0A%20%20%20%20%20%20%20%20%20%20%22sohu_urls%22%3A%20%5B%5D%2C%0A%20%20%20%20%20%20%20%20%20%20%22miaozhen_sdk_urls%22%3A%20%5B%5D%2C%0A%20%20%20%20%20%20%20%20%20%20%22admaster_sdk_urls%22%3A%20%5B%5D%2C%0A%20%20%20%20%20%20%20%20%20%20%22other_urls%22%3A%20%5B%5D%0A%20%20%20%20%20%20%20%20%7D%2C%0A%20%20%20%20%20%20%20%20%22not_interest%22%3A%20%7B%0A%20%20%20%20%20%20%20%20%20%20%22sohu_urls%22%3A%20%5B%22https%3A%2F%2Ft.ads.sohu.com%2Fcount%2Fneg%3Fimpid%3D0353435e3258ef782_0_1%26appid%3Dsquirrel%26itemspaceid%3D1000004%26viewmonitor%3De%253DP0V5jA997wz9DR6lWun16bPq6LUb42HGa9h9erROvydTo5q7cVt0Nb8zA7Ga0BIAeA9k%252FfQqCxvmD28ggECgc%252FiqzJ9itaUNOAOT2ZqSGLHpTqWCaiJ4NJDo279RPtK27JSR8SMVj%252BCmec6yeAMo2zRtNZItBgucs5BCY3yVnlDxoZR23wdAPMYd%252BXvDiCdIJ5fce9zYupiFRsBPF09oYHDWvAI87C106sNrjp1ICB7ja0iQJJy8TrMjNiVrZsBJ%252F7O5368KQMtOc3eX5D7UUtSeSY6pTI%252FHm%252B8SwXumEOk6ZtrbEikAXF1i2wsCSu3ud4RBfKwMmIBSGyXJ3vKqwUVX1UiTbRSfOmW3vmdiMRhY%252BeSeQ%252FkKKfl4aHvE%252FtQ9Uw1WIXTkwOsss%252Bi3lIqe4NKetWBegCWGp6oQKSslzg4QpMy2h98TVQsfWRoHKa30K8BiUd3I1DoJBVT93aX7FNxgtxZGTmRqsDpTT92n8DAfYmxU6ZnhH85sh8Xlc2v%252FDaV%252B5vMJMOsTJZ%252BgM0rqbwTTYXIWiDXJz8uRznkr64eQ8oqmxQOl%252FC1djqck6nJOMNmMni3whj8fonKii%252ByLuS1%252FVW6yIJ1fSvh87mn36gYqod4sGGY3t3IF9hhNveYXBkvMz9L5ZvHf2%252FZH%252FOqWynu6GvINoR%252FljJiz48QQ1zx0XKkF3TFAjfpHCrDiN0Dl2ujXS%252FW5597QDOIAI0xdAsq2BKciQJWcZ8ScKPTtWKIr6fYl9KzzyKKVLRg92Qpt9BaO0dmyUBgxzPaXtDalvg%253D%253D%2509tt2%253D1550824245422%2509turn%253D4%2509geoid1%253D1156320100%2509geoid2%253D1156320100%2509source%253Dshjtsybxpsyq%26clickmonitor%3Dc%26mkey%3D0353435e3258ef782_0_1%26deeplink%3D1%26position%3D4%26turn%3D4%26lc%3D0%26rc%3D2%26rr%3D2%26action%3D2%26ip%3D180.111.35.154%26newschn%3D157%26appv%3D3.5.57%26sdkv%3D1.5.0%26appchn%3D1%26os%3DAndroid%26osv%3D7.0%26nets%3Dwifi%26carrier%3Dunknown%26pn%3DSLA-AL00%26scs%3D72001280%26mac%3D54%3AB1%3A21%3AB8%3A76%3A2E%26imei%3D866534039422549%26imsi%3Dnull%26androidid%3D866534039422549%26did%3D2a1f3afe-22bd-3c4d-b11f-d4218d01595b%22%5D%2C%0A%20%20%20%20%20%20%20%20%20%20%22miaozhen_sdk_urls%22%3A%20%5B%5D%2C%0A%20%20%20%20%20%20%20%20%20%20%22admaster_sdk_urls%22%3A%20%5B%5D%2C%0A%20%20%20%20%20%20%20%20%20%20%22other_urls%22%3A%20%5B%5D%0A%20%20%20%20%20%20%20%20%7D%2C%0A%20%20%20%20%20%20%20%20%22discard%22%3A%20%7B%0A%20%20%20%20%20%20%20%20%20%20%22sohu_urls%22%3A%20%5B%22https%3A%2F%2Ft.ads.sohu.com%2Fcount%2Funuse%3Fimpid%3D0353435e3258ef782_0_1%26appid%3Dsquirrel%26itemspaceid%3D1000004%26viewmonitor%3De%253DP0V5jA997wz9DR6lWun16bPq6LUb42HGa9h9erROvydTo5q7cVt0Nb8zA7Ga0BIAeA9k%252FfQqCxvmD28ggECgc%252FiqzJ9itaUNOAOT2ZqSGLHpTqWCaiJ4NJDo279RPtK27JSR8SMVj%252BCmec6yeAMo2zRtNZItBgucs5BCY3yVnlDxoZR23wdAPMYd%252BXvDiCdIJ5fce9zYupiFRsBPF09oYHDWvAI87C106sNrjp1ICB7ja0iQJJy8TrMjNiVrZsBJ%252F7O5368KQMtOc3eX5D7UUtSeSY6pTI%252FHm%252B8SwXumEOk6ZtrbEikAXF1i2wsCSu3ud4RBfKwMmIBSGyXJ3vKqwUVX1UiTbRSfOmW3vmdiMRhY%252BeSeQ%252FkKKfl4aHvE%252FtQ9Uw1WIXTkwOsss%252Bi3lIqe4NKetWBegCWGp6oQKSslzg4QpMy2h98TVQsfWRoHKa30K8BiUd3I1DoJBVT93aX7FNxgtxZGTmRqsDpTT92n8DAfYmxU6ZnhH85sh8Xlc2v%252FDaV%252B5vMJMOsTJZ%252BgM0rqbwTTYXIWiDXJz8uRznkr64eQ8oqmxQOl%252FC1djqck6nJOMNmMni3whj8fonKii%252ByLuS1%252FVW6yIJ1fSvh87mn36gYqod4sGGY3t3IF9hhNveYXBkvMz9L5ZvHf2%252FZH%252FOqWynu6GvINoR%252FljJiz48QQ1zx0XKkF3TFAjfpHCrDiN0Dl2ujXS%252FW5597QDOIAI0xdAsq2BKciQJWcZ8ScKPTtWKIr6fYl9KzzyKKVLRg92Qpt9BaO0dmyUBgxzPaXtDalvg%253D%253D%2509tt2%253D1550824245422%2509turn%253D4%2509geoid1%253D1156320100%2509geoid2%253D1156320100%2509source%253Dshjtsybxpsyq%26clickmonitor%3Dc%26mkey%3D0353435e3258ef782_0_1%26deeplink%3D1%26position%3D4%26turn%3D4%26lc%3D0%26rc%3D2%26rr%3D2%26action%3D2%26ip%3D180.111.35.154%26newschn%3D157%26appv%3D3.5.57%26sdkv%3D1.5.0%26appchn%3D1%26os%3DAndroid%26osv%3D7.0%26nets%3Dwifi%26carrier%3Dunknown%26pn%3DSLA-AL00%26scs%3D72001280%26mac%3D54%3AB1%3A21%3AB8%3A76%3A2E%26imei%3D866534039422549%26imsi%3Dnull%26androidid%3D866534039422549%26did%3D2a1f3afe-22bd-3c4d-b11f-d4218d01595b%22%5D%2C%0A%20%20%20%20%20%20%20%20%20%20%22miaozhen_sdk_urls%22%3A%20%5B%5D%2C%0A%20%20%20%20%20%20%20%20%20%20%22admaster_sdk_urls%22%3A%20%5B%5D%2C%0A%20%20%20%20%20%20%20%20%20%20%22other_urls%22%3A%20%5B%5D%0A%20%20%20%20%20%20%20%20%7D%2C%0A%20%20%20%20%20%20%20%20%22timeout%22%3A%20%7B%0A%20%20%20%20%20%20%20%20%20%20%22sohu_urls%22%3A%20%5B%22https%3A%2F%2Ft.ads.sohu.com%2Fcount%2Ftoav%3Fimpid%3D0353435e3258ef782_0_1%26appid%3Dsquirrel%26itemspaceid%3D1000004%26viewmonitor%3De%253DP0V5jA997wz9DR6lWun16bPq6LUb42HGa9h9erROvydTo5q7cVt0Nb8zA7Ga0BIAeA9k%252FfQqCxvmD28ggECgc%252FiqzJ9itaUNOAOT2ZqSGLHpTqWCaiJ4NJDo279RPtK27JSR8SMVj%252BCmec6yeAMo2zRtNZItBgucs5BCY3yVnlDxoZR23wdAPMYd%252BXvDiCdIJ5fce9zYupiFRsBPF09oYHDWvAI87C106sNrjp1ICB7ja0iQJJy8TrMjNiVrZsBJ%252F7O5368KQMtOc3eX5D7UUtSeSY6pTI%252FHm%252B8SwXumEOk6ZtrbEikAXF1i2wsCSu3ud4RBfKwMmIBSGyXJ3vKqwUVX1UiTbRSfOmW3vmdiMRhY%252BeSeQ%252FkKKfl4aHvE%252FtQ9Uw1WIXTkwOsss%252Bi3lIqe4NKetWBegCWGp6oQKSslzg4QpMy2h98TVQsfWRoHKa30K8BiUd3I1DoJBVT93aX7FNxgtxZGTmRqsDpTT92n8DAfYmxU6ZnhH85sh8Xlc2v%252FDaV%252B5vMJMOsTJZ%252BgM0rqbwTTYXIWiDXJz8uRznkr64eQ8oqmxQOl%252FC1djqck6nJOMNmMni3whj8fonKii%252ByLuS1%252FVW6yIJ1fSvh87mn36gYqod4sGGY3t3IF9hhNveYXBkvMz9L5ZvHf2%252FZH%252FOqWynu6GvINoR%252FljJiz48QQ1zx0XKkF3TFAjfpHCrDiN0Dl2ujXS%252FW5597QDOIAI0xdAsq2BKciQJWcZ8ScKPTtWKIr6fYl9KzzyKKVLRg92Qpt9BaO0dmyUBgxzPaXtDalvg%253D%253D%2509tt2%253D1550824245422%2509turn%253D4%2509geoid1%253D1156320100%2509geoid2%253D1156320100%2509source%253Dshjtsybxpsyq%26clickmonitor%3Dc%26mkey%3D0353435e3258ef782_0_1%26deeplink%3D1%26position%3D4%26turn%3D4%26lc%3D0%26rc%3D2%26rr%3D2%26action%3D2%26ip%3D180.111.35.154%26newschn%3D157%26appv%3D3.5.57%26sdkv%3D1.5.0%26appchn%3D1%26os%3DAndroid%26osv%3D7.0%26nets%3Dwifi%26carrier%3Dunknown%26pn%3DSLA-AL00%26scs%3D72001280%26mac%3D54%3AB1%3A21%3AB8%3A76%3A2E%26imei%3D866534039422549%26imsi%3Dnull%26androidid%3D866534039422549%26did%3D2a1f3afe-22bd-3c4d-b11f-d4218d01595b%22%5D%0A%20%20%20%20%20%20%20%20%7D%0A%20%20%20%20%20%20%7D%2C%0A%20%20%20%20%20%20%22click_action%22%3A%20%7B%0A%20%20%20%20%20%20%20%20%22type%22%3A%201%2C%0A%20%20%20%20%20%20%20%20%22url%22%3A%20%22http%3A%2F%2Fhn1.xuanzerensheng.top%2F%22%2C%0A%20%20%20%20%20%20%20%20%22deeplink%22%3A%20%221%22%0A%20%20%20%20%20%20%7D%2C%0A%20%20%20%20%20%20%22images%22%3A%20%5B%0A%20%20%20%20%20%20%20%20%7B%0A%20%20%20%20%20%20%20%20%20%20%22name%22%3A%20%22picture%22%2C%0A%20%20%20%20%20%20%20%20%20%20%22url%22%3A%20%22https%3A%2F%2F643108e7617ef.cdn.sohucs.com%2F26e7f1b34831436c963b6fde3f023325.jpg%22%2C%0A%20%20%20%20%20%20%20%20%20%20%22width%22%3A%20%22644%22%2C%0A%20%20%20%20%20%20%20%20%20%20%22height%22%3A%20%22322%22%0A%20%20%20%20%20%20%20%20%7D%0A%20%20%20%20%20%20%5D%2C%0A%20%20%20%20%20%20%22icon%22%3A%20%7B%0A%20%20%20%20%20%20%7D%2C%0A%20%20%20%20%20%20%22video%22%3A%20%7B%0A%20%20%20%20%20%20%7D%2C%0A%20%20%20%20%20%20%22file%22%3A%20%22%22%2C%0A%20%20%20%20%20%20%22ext%22%3A%20%7B%0A%20%20%20%20%20%20%20%20%22vrpttype%22%3A%20%22%22%2C%0A%20%20%20%20%20%20%20%20%22action_call%22%3A%20%7B%0A%20%20%20%20%20%20%20%20%20%20%22type%22%3A%200%2C%0A%20%20%20%20%20%20%20%20%20%20%22url%22%3A%20%22%22%2C%0A%20%20%20%20%20%20%20%20%20%20%22click%22%3A%20%7B%0A%20%20%20%20%20%20%20%20%20%20%20%20%22sohu_urls%22%3A%20%5B%5D%2C%0A%20%20%20%20%20%20%20%20%20%20%20%20%22miaozhen_sdk_urls%22%3A%20%5B%5D%2C%0A%20%20%20%20%20%20%20%20%20%20%20%20%22admaster_sdk_urls%22%3A%20%5B%5D%2C%0A%20%20%20%20%20%20%20%20%20%20%20%20%22other_urls%22%3A%20%5B%5D%0A%20%20%20%20%20%20%20%20%20%20%7D%0A%20%20%20%20%20%20%20%20%7D%2C%0A%20%20%20%20%20%20%20%20%22flag_sensitive%22%3A%220%22%0A%20%20%20%20%20%20%7D%0A%20%20%20%20%7D%0A%20%20%5D%0A%7D%0A",
  "loadid": "86706023ee240"
}